Workbook

Sheet 1. Executive Dashboard
A1: DAILYOBJECTS | TACTICAL REVENUE GROWTH PLAYBOOK
A2: Executive Dashboard · 57 tactical ideas · evidence: GA4 (India web+app) 2025-08-01 to 2026-07-31 + internal files + 52 D2C brand tactics · Priority = RevImpact x Confidence x Ease x Speed x MarginFriendly (/100)
A4: TOP 5 BETS — what we would launch immediately | P4: Ideas by Revenue Lever
A5: # | B5: Bet | C5: Target customer | D5: Category / SKUs | E5: Revenue mechanism | F5: Expected impact | G5: Margin | H5: Time to launch | P5: CVR | Q5: =COUNTIF('2. Master Opportunity List'!$E$4:$E$60,"CVR")
A6: 1 | B6: Close the mobile & payment conversion gap (ID11+ID12+ID47) | C6: 91% of traffic (mobile) + all checkout, esp. payment-stage droppers | D6: Cross-category / checkout | E6: Mobile is 49M sessions at 0.95% CVR vs 1.96% desktop; 42% drop after add-payment-info. Fix mobile PDP/checkout + UPI express + failed-payment retry. | F6: Very High - largest single prize; +0.3-0.5pp mobile CVR = ~₹150-400M | G6: Accretive (RTO down) | H6: <14-30 days | P6: AOV | Q6: =COUNTIF('2. Master Opportunity List'!$E$4:$E$60,"AOV")
A7: 2 | B7: Phone-case attach engine + FBT (ID01+ID13) | C7: Every case buyer (57% of all product views) | D7: Phone Cases + screen guard/grip/charm (1101,1103,1815,1812) | E7: Cases draw 31M views at ASP ~₹1,068; attach a 30-50%-off screen guard/grip in PDP+cart. High-margin accessory attach. | F7: High - +8-15% AOV on the biggest-traffic category | G7: Accretive | H7: <7 days | P7: Frequency | Q7: =COUNTIF('2. Master Opportunity List'!$E$4:$E$60,"Frequency")
A8: 3 | B8: Turn on lifecycle CRM (abandonment, browse, O1->O2, SMS/WhatsApp) (ID19,20,24,47,18) | C8: Abandoners, browsers, first-order buyers, owned base | D8: Cross-category | E8: Owned channels are ~0.55% of revenue today despite SMS converting at 4.2%. 1.5M checkout-abandoners/yr. Build flows + scale SMS/WA. | F8: High - recover lost demand; ₹50-150M owned-channel upside | G8: Accretive | H8: <7-14 days | P8: Traffic Monetisation | Q8: =COUNTIF('2. Master Opportunity List'!$E$4:$E$60,"Traffic Monetisation")
A9: 4 | B9: Cart free-gift ladder + threshold architecture (ID06+ID49+ID07) | C9: All carts near threshold; new users at ₹2,299 | D9: Cross-category / GWP | E9: Anchor a gift ladder at ₹1,999/₹2,999 (high perceived value, low COGS) + align WELCOME300 + prepaid free-ship. Pull baskets up without % discounts. | F9: High - +6-12% AOV | G9: Neutral (gift COGS < uplift) | H9: <7-14 days | P9: Cross-category Purchase | Q9: =COUNTIF('2. Master Opportunity List'!$E$4:$E$60,"Cross-category Purchase")
A10: 5 | B10: Ecosystem bundles: power-bank+case & bag carry-system (ID02+ID03+ID04) | C10: Power-bank, bag & watch-band shoppers | D10: Power banks (1809), Bags (1201-04), Watch bands (1801) | E10: Highest-revenue + high-consideration categories; MagSafe/carry interoperability makes bundles natural. Power bank+case, bag+sleeve+organiser, multi-band. | F10: High - +10-25% AOV on premium baskets | G10: Accretive/Neutral | H10: <7-14 days | P10: Category Penetration | Q10: =COUNTIF('2. Master Opportunity List'!$E$4:$E$60,"Category Penetration")
P11: Revenue from CRM audiences | Q11: =COUNTIF('2. Master Opportunity List'!$E$4:$E$60,"Revenue from CRM audiences")
A12: PORTFOLIO AT A GLANCE | P12: New User Conversion | Q12: =COUNTIF('2. Master Opportunity List'!$E$4:$E$60,"New User Conversion")
A13: =COUNTA('2. Master Opportunity List'!$A$4:$A$60) | D13: =COUNTIF('2. Master Opportunity List'!$AH$4:$AH$60,">=4") | G13: =COUNTIF('2. Master Opportunity List'!$AG$4:$AG$60,"Same Day")+COUNTIF('2. Master Opportunity List'!$AG$4:$AG$60,"1-3 Days")+COUNTIF('2. Master Opportunity List'!$AG$4:$AG$60,"4-7 Days") | J13: =COUNTIF('2. Master Opportunity List'!$AB$4:$AB$60,"N") | P13: Checkout Completion | Q13: =COUNTIF('2. Master Opportunity List'!$E$4:$E$60,"Checkout Completion")
A14: Total ideas | D14: High-impact (RevImpact>=4) | G14: Launchable <=7 days | J14: Require NO discount | P14: Revenue from existing traffic | Q14: =COUNTIF('2. Master Opportunity List'!$E$4:$E$60,"Revenue from existing traffic")
P15: Contribution margin | Q15: =COUNTIF('2. Master Opportunity List'!$E$4:$E$60,"Contribution margin")
A16: =COUNTIF('2. Master Opportunity List'!$E$4:$E$60,"AOV") | D16: =COUNTIF('2. Master Opportunity List'!$E$4:$E$60,"CVR") | G16: =COUNTIF('2. Master Opportunity List'!$E$4:$E$60,"Frequency")+COUNTIF('2. Master Opportunity List'!$E$4:$E$60,"Revenue from CRM audiences") | J16: =COUNTIF('2. Master Opportunity List'!$E$4:$E$60,"Cross-category Purchase")+COUNTIF('2. Master Opportunity List'!$E$4:$E$60,"Category Penetration")
A17: AOV-focused | D17: CVR-focused | G17: Retention/CRM-focused | J17: Cross-sell / category
P18: Ideas by Time to Launch
P19: Same Day | Q19: =COUNTIF('2. Master Opportunity List'!$AG$4:$AG$60,"Same Day")
P20: 1-3 Days | Q20: =COUNTIF('2. Master Opportunity List'!$AG$4:$AG$60,"1-3 Days")
A21: TOP 10 REVENUE OPPORTUNITIES (live-linked to Master list, ranked by Priority) | P21: 4-7 Days | Q21: =COUNTIF('2. Master Opportunity List'!$AG$4:$AG$60,"4-7 Days")
A22: Rank | B22: Initiative | C22: Category | D22: Segment | E22: Revenue Lever | F22: Impact | G22: Confidence(1-5) | H22: Effort | I22: Time to Launch | J22: Margin | K22: Priority(/100) | P22: 8-14 Days | Q22: =COUNTIF('2. Master Opportunity List'!$AG$4:$AG$60,"8-14 Days")
A23: 1 | B23: ='2. Master Opportunity List'!C4 | C23: ='2. Master Opportunity List'!J4 | D23: ='2. Master Opportunity List'!I4 | E23: ='2. Master Opportunity List'!E4 | F23: ='2. Master Opportunity List'!Z4 | G23: ='2. Master Opportunity List'!AI4 | H23: ='2. Master Opportunity List'!AF4 | I23: ='2. Master Opportunity List'!AG4 | J23: ='2. Master Opportunity List'!AA4 | K23: ='2. Master Opportunity List'!AM4 | P23: 15-30 Days | Q23: =COUNTIF('2. Master Opportunity List'!$AG$4:$AG$60,"15-30 Days")
A24: 2 | B24: ='2. Master Opportunity List'!C5 | C24: ='2. Master Opportunity List'!J5 | D24: ='2. Master Opportunity List'!I5 | E24: ='2. Master Opportunity List'!E5 | F24: ='2. Master Opportunity List'!Z5 | G24: ='2. Master Opportunity List'!AI5 | H24: ='2. Master Opportunity List'!AF5 | I24: ='2. Master Opportunity List'!AG5 | J24: ='2. Master Opportunity List'!AA5 | K24: ='2. Master Opportunity List'!AM5
A25: 3 | B25: ='2. Master Opportunity List'!C6 | C25: ='2. Master Opportunity List'!J6 | D25: ='2. Master Opportunity List'!I6 | E25: ='2. Master Opportunity List'!E6 | F25: ='2. Master Opportunity List'!Z6 | G25: ='2. Master Opportunity List'!AI6 | H25: ='2. Master Opportunity List'!AF6 | I25: ='2. Master Opportunity List'!AG6 | J25: ='2. Master Opportunity List'!AA6 | K25: ='2. Master Opportunity List'!AM6
A26: 4 | B26: ='2. Master Opportunity List'!C7 | C26: ='2. Master Opportunity List'!J7 | D26: ='2. Master Opportunity List'!I7 | E26: ='2. Master Opportunity List'!E7 | F26: ='2. Master Opportunity List'!Z7 | G26: ='2. Master Opportunity List'!AI7 | H26: ='2. Master Opportunity List'!AF7 | I26: ='2. Master Opportunity List'!AG7 | J26: ='2. Master Opportunity List'!AA7 | K26: ='2. Master Opportunity List'!AM7 | P26: Ideas by Category
A27: 5 | B27: ='2. Master Opportunity List'!C8 | C27: ='2. Master Opportunity List'!J8 | D27: ='2. Master Opportunity List'!I8 | E27: ='2. Master Opportunity List'!E8 | F27: ='2. Master Opportunity List'!Z8 | G27: ='2. Master Opportunity List'!AI8 | H27: ='2. Master Opportunity List'!AF8 | I27: ='2. Master Opportunity List'!AG8 | J27: ='2. Master Opportunity List'!AA8 | K27: ='2. Master Opportunity List'!AM8 | P27: Apple Watch Bands | Q27: =COUNTIF('2. Master Opportunity List'!$J$4:$J$60,"Apple Watch Bands")
A28: 6 | B28: ='2. Master Opportunity List'!C9 | C28: ='2. Master Opportunity List'!J9 | D28: ='2. Master Opportunity List'!I9 | E28: ='2. Master Opportunity List'!E9 | F28: ='2. Master Opportunity List'!Z9 | G28: ='2. Master Opportunity List'!AI9 | H28: ='2. Master Opportunity List'!AF9 | I28: ='2. Master Opportunity List'!AG9 | J28: ='2. Master Opportunity List'!AA9 | K28: ='2. Master Opportunity List'!AM9 | P28: Backpacks | Q28: =COUNTIF('2. Master Opportunity List'!$J$4:$J$60,"Backpacks")
A29: 7 | B29: ='2. Master Opportunity List'!C10 | C29: ='2. Master Opportunity List'!J10 | D29: ='2. Master Opportunity List'!I10 | E29: ='2. Master Opportunity List'!E10 | F29: ='2. Master Opportunity List'!Z10 | G29: ='2. Master Opportunity List'!AI10 | H29: ='2. Master Opportunity List'!AF10 | I29: ='2. Master Opportunity List'!AG10 | J29: ='2. Master Opportunity List'!AA10 | K29: ='2. Master Opportunity List'!AM10 | P29: Cross-category | Q29: =COUNTIF('2. Master Opportunity List'!$J$4:$J$60,"Cross-category")
A30: 8 | B30: ='2. Master Opportunity List'!C11 | C30: ='2. Master Opportunity List'!J11 | D30: ='2. Master Opportunity List'!I11 | E30: ='2. Master Opportunity List'!E11 | F30: ='2. Master Opportunity List'!Z11 | G30: ='2. Master Opportunity List'!AI11 | H30: ='2. Master Opportunity List'!AF11 | I30: ='2. Master Opportunity List'!AG11 | J30: ='2. Master Opportunity List'!AA11 | K30: ='2. Master Opportunity List'!AM11 | P30: Desk Organisers | Q30: =COUNTIF('2. Master Opportunity List'!$J$4:$J$60,"Desk Organisers")
A31: 9 | B31: ='2. Master Opportunity List'!C12 | C31: ='2. Master Opportunity List'!J12 | D31: ='2. Master Opportunity List'!I12 | E31: ='2. Master Opportunity List'!E12 | F31: ='2. Master Opportunity List'!Z12 | G31: ='2. Master Opportunity List'!AI12 | H31: ='2. Master Opportunity List'!AF12 | I31: ='2. Master Opportunity List'!AG12 | J31: ='2. Master Opportunity List'!AA12 | K31: ='2. Master Opportunity List'!AM12 | P31: Gifting | Q31: =COUNTIF('2. Master Opportunity List'!$J$4:$J$60,"Gifting")
A32: 10 | B32: ='2. Master Opportunity List'!C13 | C32: ='2. Master Opportunity List'!J13 | D32: ='2. Master Opportunity List'!I13 | E32: ='2. Master Opportunity List'!E13 | F32: ='2. Master Opportunity List'!Z13 | G32: ='2. Master Opportunity List'!AI13 | H32: ='2. Master Opportunity List'!AF13 | I32: ='2. Master Opportunity List'!AG13 | J32: ='2. Master Opportunity List'!AA13 | K32: ='2. Master Opportunity List'!AM13 | P32: Impulse tech | Q32: =COUNTIF('2. Master Opportunity List'!$J$4:$J$60,"Impulse tech")
P33: Phone Cases | Q33: =COUNTIF('2. Master Opportunity List'!$J$4:$J$60,"Phone Cases")
P34: Power Banks | Q34: =COUNTIF('2. Master Opportunity List'!$J$4:$J$60,"Power Banks")
P35: Tech Organisers | Q35: =COUNTIF('2. Master Opportunity List'!$J$4:$J$60,"Tech Organisers")
P36: Wallets | Q36: =COUNTIF('2. Master Opportunity List'!$J$4:$J$60,"Wallets")

Sheet 2. Master Opportunity List
A1: MASTER REVENUE OPPORTUNITY LIST
A2: Every idea = one row. Filterable. Priority = RevImpact x Confidence x Ease x Speed x MarginFriendly, normalised /100. Evidence source: GA4 'DO - GA4' (273672074), via Windsor.ai, pulled 2026-08-10
A3: Idea ID | B3: Rank | C3: Initiative Name | D3: Detailed Mechanic | E3: Revenue Lever | F3: Primary KPI | G3: Secondary KPI | H3: Target Customer | I3: Cohort | J3: Category | K3: Subcategory | L3: Specific SKU(s) | M3: Trigger | N3: Offer / Proposition | O3: Website Placement | P3: Channel | Q3: Journey Stage | R3: External Brand Example | S3: Benchmark Mechanic | T3: Source URL | U3: DailyObjects Evidence (OBS/INF/HYP) | V3: Why It Should Work | W3: Expected Behaviour Change | X3: Exp. CVR Impact | Y3: Exp. AOV Impact | Z3: Exp. Revenue Impact | AA3: Exp. Margin Impact | AB3: Discount? | AC3: Est. Disc % | AD3: Gift? | AE3: Technology Dependency | AF3: Implementation Effort | AG3: Time to Launch | AH3: Rev Impact (1-5) | AI3: Confidence (1-5) | AJ3: Ease (1-5) | AK3: Speed (1-5) | AL3: Margin-Friendly (1-5) | AM3: Priority (/100) | AN3: Recommended Test | AO3: Success Metric | AP3: Guardrail Metric | AQ3: Owner | AR3: Status | AS3: Notes
A4: ID01 | B4: 1 | C4: Phone Case Attach Engine (screen guard + charm + strap) | D4: On every phone-case PDP + cart, show a 'Complete your case' rail: matching tempered-glass screen guard, MagSafe charm/grip and lanyard at 30-50% off ONLY when added with the case. Auto-apply in cart. | E4: AOV | F4: Units per Transaction | G4: AOV | H4: All case buyers | I4: New & Repeat | J4: Phone Cases | K4: Screen guards / grips / straps | L4: 1101,1103,1815,1812 | M4: View/ATC of any phone case | N4: 30-50% off attach items with a case | O4: PDP below CTA + Cart FBT rail | P4: Website/App | Q4: Consideration/Cart | R4: Casetify (up to 50% off accy with case); dbrand Grip+Prism; Nomad 15% off 2 | S4: Accessory-attach discount on hero product | T4: couponfollow.com/site/casetify.com | U4: OBS: Phone cases = 31.1M item views (57% of all views) but ASP only ~Rs1,068 & view->purchase 1.2%; screen guards(1815)/grips(1812) already sell at high ATC rates. Massive under-monetised traffic. | V4: The case is the wedge; a discounted, compatible attach is the single most proven case-AOV lever across every accessory peer. | W4: Case-only buyers add 1-2 low-cost high-margin accessories. | X4: Neutral | Y4: +8-15% | Z4: High | AA4: Accretive (accy high margin even at 40% off) | AB4: Y | AC4: 0.4 | AD4: N | AE4: Merch rule / FBT widget | AF4: Easy | AG4: 4-7 Days | AH4: 5 | AI4: 5 | AJ4: 4 | AK4: 4 | AL4: 4 | AM4: =ROUND(AH4*AI4*AJ4*AK4*AL4/3125*100,1) | AN4: A/B PDP+cart attach rail vs control on iPhone case PDPs | AO4: +Rs AOV & UPT on case orders | AP4: Case CVR, return rate | AQ4: Unassigned | AR4: Backlog
A5: ID19 | B5: 2 | C5: Cart & checkout abandonment flow (email+SMS+push) | D5: 3-step abandonment series: 30min reminder, 24h with social proof, 48h with a modest incentive/free-ship reminder. Trigger separately for ATC-abandon vs checkout-abandon. | E5: CVR | F5: Revenue from CRM audiences | G5: Checkout Completion | H5: Abandoners | I5: High-intent non-purchasers | J5: Cross-category | K5: Abandonment | L5: all | M5: ATC/checkout without purchase | N5: Reminder; light incentive on step 3 | O5: Email/SMS/Push | P5: CRM | Q5: Recovery | R5: Standard Klaviyo flows; boAt/Mamaearth CRM | T5: internal best practice | U5: OBS: 5.99M add-to-cart vs 623k purchase; begin_checkout 1.55M -> purchase 623k. Email+SMS+Push together only ~0.55% of revenue (Rs7.35M) - flows are under-built. | V5: Recovering even a small % of the 1.5M checkout-abandoners is large; owned channels are near-free and currently dormant. | W5: Returns to complete purchase. | X5: + | Y5: Neutral | Z5: High | AA5: Accretive | AB5: Y | AC5: 0.05 | AD5: N | AE5: CRM/ESP flows + events | AF5: Easy | AG5: 4-7 Days | AH5: 5 | AI5: 5 | AJ5: 4 | AK5: 4 | AL5: 4 | AM5: =ROUND(AH5*AI5*AJ5*AK5*AL5/3125*100,1) | AN5: Flow on vs holdout | AO5: Recovered revenue per abandoner | AP5: Unsub rate, discount leakage | AQ5: Unassigned | AR5: Backlog
A6: ID05 | B6: 3 | C6: Cart low-price add-on rail (impulse SKUs) | D6: In cart, show a horizontal 'Add for a little more' rail of high-margin impulse SKUs <Rs499 (cable binds, screen guards, grips, coasters, charms) one-tap add. | E6: AOV | F6: Units per Transaction | G6: AOV | H6: All carts | I6: New & Repeat | J6: Impulse tech | K6: Cables/grips/guards/charms | L6: 1811,1812,1815,1705 | M6: Cart view | N6: No discount - convenience placement | O6: Cart add-on rail | P6: Website/App | Q6: Cart | R6: Amazon-style add-ons; Nykaa mini rail | T6: internal best practice | U6: OBS: Wrap-Lock cable bind is a top-review bestseller; grips(1812)/screen guards(1815) show very high ATC-to-view. Cheap, high-margin impulse inventory exists. | V6: Frictionless one-tap add of a cheap complement is pure incremental margin with zero discount. | W6: Adds a sub-Rs499 impulse item. | X6: Neutral | Y6: +3-6% | Z6: Med | AA6: Accretive (no discount) | AB6: N | AC6: 0 | AD6: N | AE6: Cart widget | AF6: Very Easy | AG6: 4-7 Days | AH6: 3 | AI6: 4 | AJ6: 5 | AK6: 5 | AL6: 5 | AM6: =ROUND(AH6*AI6*AJ6*AK6*AL6/3125*100,1) | AN6: Add-on rail vs control | AO6: Attach rate of add-on SKUs | AP6: Cart abandonment | AQ6: Unassigned | AR6: Backlog
A7: ID27 | B7: 4 | C7: Bestseller & high-margin SKU prioritisation on PLP/home | D7: Re-sort PLPs and homepage rails to lead with proven high-CVR, high-margin bestsellers (Wrap-Lock cable, Orbis sling, Valet tray, Loop power banks, top case models); pin 'Bestseller' badges. | E7: CVR | F7: Conversion Rate | G7: Revenue per Visitor | H7: All browsers | I7: New & Repeat | J7: Cross-category | K7: Merch sort | L7: bestsellers | M7: PLP/home view | N7: None | O7: PLP sort + homepage | P7: Website/App | Q7: Discovery | R7: Merch best practice; DO's own SKU-cull->sales lift | T7: d2cx.co | U7: OBS: DO grew by cutting 72->35 SKUs to focus on bestsellers (Rs50L->Rs2Cr/mo). Homepage CVR 1.54% vs /collection 0.33% - sorting matters. | V7: Leading with proven winners raises blended CVR and margin without new traffic. | W7: Sees winners first; converts faster. | X7: + | Y7: Slight + | Z7: Med | AA7: Accretive | AB7: N | AC7: 0 | AD7: N | AE7: Merch sort rules | AF7: Very Easy | AG7: Same Day | AH7: 3 | AI7: 4 | AJ7: 5 | AK7: 5 | AL7: 5 | AM7: =ROUND(AH7*AI7*AJ7*AK7*AL7/3125*100,1) | AN7: Bestseller-first sort vs default | AO7: PLP CVR, RPV | AP7: Long-tail exposure | AQ7: Unassigned | AR7: Backlog
A8: ID07 | B8: 5 | C8: Prepaid free-shipping + Rs79 COD-fee reframing | D8: Make free shipping explicit and prepaid-gated with a visible bar ('You're Rs X from free shipping - pay online'); show the Rs79 COD fee as a saveable line at checkout with a one-tap 'Switch to UPI & save Rs79 + free ship'. | E8: CVR | F8: Checkout Completion | G8: Contribution margin | H8: COD-inclined shoppers | I8: New | J8: Cross-category | K8: Shipping/payment | L8: all | M8: Checkout w/ COD selected | N8: Free ship + waive COD fee on prepaid | O8: Cart + Checkout | P8: Website/App | Q8: Checkout | R8: boAt/Zouk/Mamaearth prepaid incentives; Souled Store Rs499 free-ship | T8: grabon.in/mamaearth | U8: OBS: add_payment_info->purchase only 58% (large payment-stage drop); India COD RTO is a known margin leak. INF: existing free-ship thresholds reported inconsistently (Rs749 vs Rs1,199) - reframe clearly. | V8: Shifting COD->prepaid cuts RTO cost and lifts contribution margin more than the shipping given away; clarity reduces checkout abandonment. | W8: Chooses prepaid; completes checkout. | X8: + | Y8: Neutral | Z8: High | AA8: Accretive (RTO saved) | AB8: N | AC8: 0 | AD8: N | AE8: Checkout config | AF8: Easy | AG8: 4-7 Days | AH8: 4 | AI8: 4 | AJ8: 4 | AK8: 4 | AL8: 5 | AM8: =ROUND(AH8*AI8*AJ8*AK8*AL8/3125*100,1) | AN8: Prepaid nudge + COD-fee reframing at checkout | AO8: Prepaid share, checkout completion | AP8: Overall CVR | AQ8: Unassigned | AR8: Backlog
A9: ID02 | B9: 6 | C9: Power Bank + MagSafe Case cross-sell bundle | D9: On Loop Qi2 power-bank PDPs, add 'Powers up perfectly with' a MagSafe case at bundle price = power bank + case -10%. Reverse: on MagSafe case PDPs surface Loop power bank. | E9: AOV | F9: Cross-category Purchase | G9: AOV | H9: Power-bank & MagSafe shoppers | I9: New & Repeat | J9: Power Banks | K9: MagSafe cases | L9: 1809,1103 | M9: View Loop Qi2 PDP | N9: Bundle -10% vs buying separately | O9: PDP FBT + Cart | P9: Website/App | Q9: Consideration | R9: Anker charger+cable combo; Peak Design ecosystem | T9: anker.com/collections/bundles | U9: OBS: Power banks = highest revenue category (Rs397M, ASP Rs3,108); MagSafe cases 42k units. Both MagSafe-ecosystem; natural attach. Loop 10000mAh PDP alone did Rs10.1M. | V9: Qi2/MagSafe interoperability is a real functional reason to pair; premium buyers are least price-sensitive. | W9: Power-bank buyers add a MagSafe case (and vice-versa). | X9: Neutral | Y9: +10-18% | Z9: High | AA9: Neutral | AB9: Y | AC9: 0.1 | AD9: N | AE9: FBT widget | AF9: Easy | AG9: 4-7 Days | AH9: 4 | AI9: 4 | AJ9: 4 | AK9: 4 | AL9: 4 | AM9: =ROUND(AH9*AI9*AJ9*AK9*AL9/3125*100,1) | AN9: Bundle module on Loop PDPs | AO9: Attach rate power bank<->case | AP9: Power bank CVR | AQ9: Unassigned | AR9: Backlog
A10: ID04 | B10: 7 | C10: Watch-band multi-pack ('Band Wardrobe') | D10: On Apple Watch band PDPs offer buy-2-save-15% / buy-3-save-20% across bands (mix leather/sport/nylon). 'Build your band wardrobe' selector. | E10: AOV | F10: Units per Transaction | G10: AOV | H10: Watch-band shoppers | I10: New & Repeat | J10: Apple Watch Bands | K10: Bands | L10: 1801 | M10: View watch-band PDP/PLP | N10: Buy 2 -15%, 3+ -20% | O10: PDP selector + PLP banner | P10: Website/App | Q10: Consideration | R10: Casetify escalator 15/20/30; Noise FEST15/20 | T10: simplycodes.com/store/casetify.com | U10: OBS: Watch bands 107k units, ASP Rs1,108, Rs118.8M - a fashion-rotation SKU bought in multiples elsewhere. Ecosystem/repeat role. | V10: Bands are a wardrobe item (match outfit/occasion); multi-buy escalators convert single-band intent into 2-3. | W10: Single-band buyers add a 2nd/3rd band. | X10: Neutral | Y10: +12-20% | Z10: Med-High | AA10: Accretive | AB10: Y | AC10: 0.17 | AD10: N | AE10: Qty-tier promo | AF10: Easy | AG10: 4-7 Days | AH10: 4 | AI10: 4 | AJ10: 4 | AK10: 4 | AL10: 4 | AM10: =ROUND(AH10*AI10*AJ10*AK10*AL10/3125*100,1) | AN10: Multi-band escalator on band PDPs | AO10: UPT on band orders | AP10: Band margin | AQ10: Unassigned | AR10: Backlog
A11: ID51 | B11: 8 | C11: Reviews & UGC amplification on high-traffic PDPs | D11: Surface photo reviews, review count and Q&A prominently on top PDPs; seed Q&A for compatibility questions (fits which phone) to cut pre-purchase doubt. | E11: CVR | F11: Conversion Rate | G11: New User Conversion | H11: PDP visitors | I11: New | J11: Cross-category | K11: Social proof | L11: top PDPs | M11: PDP view | N11: None | O11: PDP | P11: Website/App | Q11: Consideration | R11: Review-led PDPs; DO VoC (80k+ reviews) | T11: internal VoC deck (80,303 reviews / 11,771 SKUs) | U11: OBS: DO has 80,303 reviews across 11,771 SKUs (VoC deck) - a huge, under-surfaced trust asset; PDPs already show ratings. | V11: Photo reviews + compatibility Q&A directly reduce the doubts that stall accessory purchases. | W11: Trusts and converts. | X11: + | Y11: Neutral | Z11: Med | AA11: Accretive | AB11: N | AC11: 0 | AD11: N | AE11: Reviews widget | AF11: Easy | AG11: 4-7 Days | AH11: 3 | AI11: 4 | AJ11: 4 | AK11: 4 | AL11: 5 | AM11: =ROUND(AH11*AI11*AJ11*AK11*AL11/3125*100,1) | AN11: Enhanced reviews vs control | AO11: PDP CVR | AP11: Review authenticity | AQ11: Unassigned | AR11: Backlog
A12: ID53 | B12: 9 | C12: Prepaid-only deeper offer to convert COD share | D12: Offer the best price/gift ONLY on prepaid (COD gets base price); reframe as 'prepaid perks' not a COD penalty. Protects margin via RTO reduction. | E12: Contribution margin | F12: Contribution margin | G12: Checkout Completion | H12: COD-preferring | I12: New | J12: Cross-category | K12: Prepaid gating | L12: all | M12: Payment selection | N12: Prepaid-only extra 5% / gift | O12: Checkout | P12: Website/App | Q12: Checkout | R12: WOW 'buy 3 pay 2' prepaid-only; boAt prepaid | T12: picodi.com/in/wow-skin-science | U12: OBS: payment-stage drop + India RTO economics; prepaid gating is standard and margin-accretive. | V12: Shifting COD->prepaid saves RTO/logistics cost that exceeds the incentive - net margin gain. | W12: Chooses prepaid. | X12: Neutral/+ | Y12: Neutral | Z12: Med | AA12: Accretive | AB12: Y | AC12: 0.05 | AD12: N | AE12: Checkout rules | AF12: Easy | AG12: 4-7 Days | AH12: 3 | AI12: 4 | AJ12: 4 | AK12: 4 | AL12: 5 | AM12: =ROUND(AH12*AI12*AJ12*AK12*AL12/3125*100,1) | AN12: Prepaid-only offer vs universal | AO12: Prepaid share, contribution/order | AP12: Overall CVR | AQ12: Unassigned | AR12: Backlog
A13: ID12 | B13: 10 | C13: Express/1-tap payment (UPI intent, wallets, tokenised cards) | D13: Add UPI-intent one-tap, popular wallets, saved/tokenised cards and a prominent 'Pay by UPI' default; add payment-failure retry with auto-fallback + 'complete your payment' recovery link. | E13: CVR | F13: Checkout Completion | G13: Revenue per Visitor | H13: All checkout | I13: New & Repeat | J13: Cross-category | K13: Payments | L13: all | M13: add_payment_info reached | N13: None | O13: Payment page | P13: Website/App | Q13: Payment | R13: boAt/Boult UPI cashback; standard India PSP stack | T13: grabon.in/boat-coupons | U13: OBS: add_payment_info=1.07M but purchase=623k -> 42% drop AFTER entering payment. /payment-processing route shows real fallout. Payment friction/failure is a top leak. | V13: A large share of the payment-stage drop is failed/abandoned payment, directly recoverable with better methods + retry. | W13: Completes payment; recovers failed attempts. | X13: ++ | Y13: Neutral | Z13: Very High | AA13: Accretive | AB13: N | AC13: 0 | AD13: N | AE13: PSP integration + retry flow | AF13: Moderate | AG13: 8-14 Days | AH13: 5 | AI13: 4 | AJ13: 3 | AK13: 3 | AL13: 5 | AM13: =ROUND(AH13*AI13*AJ13*AK13*AL13/3125*100,1) | AN13: New payment stack vs control; payment success rate | AO13: Payment success %, checkout completion | AP13: Fraud, chargebacks | AQ13: Unassigned | AR13: Backlog
A14: ID18 | B14: 11 | C14: Second-order accelerator coupon on thank-you + email | D14: Give every first-time buyer a time-boxed next-order incentive (e.g. Rs200 off next order within 30 days, min Rs1,499) on the thank-you page and in the order-confirmation email/SMS. | E14: Frequency | F14: Repeat Purchase | G14: O1->O2 rate | H14: First-order buyers | I14: O1 | J14: Cross-category | K14: Repeat incentive | L14: all | M14: First purchase | N14: Rs200 off next order in 30 days (min Rs1,499) | O14: Thank-you + email/SMS | P14: CRM | Q14: Post-purchase | R14: Gymshark loyalty; Sugar points; standard O1->O2 | T14: gymshark.com/pages/loyalty-free-next-day | U14: OBS: Returning users convert 2.56x new (1.77% vs 0.69%) & higher AOV (Rs2,573) - accelerating O1->O2 compounds. Repeat rate reported ~47%. | V14: The O1->O2 jump is the highest-leverage retention moment; a bounded incentive pulls the second order forward. | W14: Places a 2nd order sooner. | X14: Neutral | Y14: Neutral | Z14: High | AA14: Dilutive (control redemption) | AB14: Y | AC14: 0.13 | AD14: N | AE14: Coupon + CRM flow | AF14: Easy | AG14: 4-7 Days | AH14: 4 | AI14: 4 | AJ14: 4 | AK14: 4 | AL14: 3 | AM14: =ROUND(AH14*AI14*AJ14*AK14*AL14/3125*100,1) | AN14: O1 cohort with vs without coupon | AO14: 30/60-day repeat rate | AP14: Margin, redemption cannibalisation | AQ14: Unassigned | AR14: Backlog
A15: ID28 | B15: 12 | C15: First-order offer clarity + email/phone capture popup | D15: Tighten the welcome popup: 'Get Rs300 off your first order over Rs2,299 - unlock now' with email+phone capture, then persist the code in a sticky bar. Route to a first-time-buyer LP. | E15: New User Conversion | F15: New User Conversion | G15: Revenue from CRM audiences | H15: New visitors | I15: New | J15: Cross-category | K15: First-order + capture | L15: all | M15: First visit / exit intent | N15: WELCOME300 (Rs300 off > Rs2,299) | O15: Popup + sticky bar + LP | P15: Website/App/CRM | Q15: Acquisition | R15: Sugar 500pts signup; Mamaearth; standard welcome | T15: sugarcosmetics.com/pages/faqs | U15: OBS: WELCOME300 already exists but new CVR is only 0.69%; capture feeds the dormant CRM base. INF: popup value/persistence likely weak. | V15: First-order clarity + capture both lifts new CVR and builds the owned audience that CRM ideas monetise. | W15: Signs up; completes first order. | X15: + | Y15: Neutral (threshold Rs2,299) | Z15: Med-High | AA15: Neutral | AB15: Y | AC15: 0.13 | AD15: N | AE15: Popup + CRM | AF15: Easy | AG15: 4-7 Days | AH15: 4 | AI15: 4 | AJ15: 4 | AK15: 4 | AL15: 3 | AM15: =ROUND(AH15*AI15*AJ15*AK15*AL15/3125*100,1) | AN15: New popup vs current | AO15: Capture rate, new-user CVR | AP15: Discount on would-buy-anyway | AQ15: Unassigned | AR15: Backlog
A16: ID39 | B16: 13 | C16: Return/exchange-friendly messaging to unlock high-consideration bags | D16: Add prominent easy-returns + warranty + '30-day trial' style reassurance on backpack/luggage/premium-bag PDPs; show real reviews & durability proof. | E16: CVR | F16: Conversion Rate | G16: Category Penetration | H16: Bag shoppers | I16: New | J16: Backpacks | K16: Risk reversal | L16: 1201,1202 | M16: Bag PDP | N16: Trial/returns reassurance | O16: Bag PDPs | P16: Website/App | Q16: Consideration | R16: Mokobara 30-day trial + warranty | T16: grabon.in/mokobara | U16: OBS: Backpacks view->purchase 0.77% & ATC rate 3.7% (lowest of big cats) - classic high-consideration hesitation on a Rs1,900+ ASP item. | V16: Premium bag hesitation is about risk; explicit reversal is Mokobara's proven unlock. | W16: Commits to a considered bag purchase. | X16: + | Y16: Neutral | Z16: Med | AA16: Neutral (returns cost) | AB16: N | AC16: 0 | AD16: N | AE16: PDP content + returns policy | AF16: Easy | AG16: 4-7 Days | AH16: 3 | AI16: 4 | AJ16: 4 | AK16: 4 | AL16: 4 | AM16: =ROUND(AH16*AI16*AJ16*AK16*AL16/3125*100,1) | AN16: Risk-reversal messaging vs control on bag PDPs | AO16: Bag CVR | AP16: Return rate | AQ16: Unassigned | AR16: Backlog
... A60: ID40 | B60: 57 | C60: Paid low-cost membership ('DO Club') | D60: Test a Rs299/6-month membership: free shipping no-min + extra 5% + early access to drops + birthday gift. Pitch at checkout to repeat buyers. | E60: Frequency | F60: Repeat Purchase | G60: AOV | H60: Repeat buyers | I60: O2/O3+ | J60: Cross-category | K60: Membership | L60: all | M60: Checkout / account | N60: Rs299/6mo perks | O60: Checkout + account | P60: Website/App | Q60: Retention | R60: Mokobara Moko Club Rs499; Bewakoof TriBe Rs99 | T60: grabon.in/mokobara | U60: INF: repeat cohort = 57% of revenue; a paid membership converts free-shipping into a retention loop & prepaid float. | V60: Sunk-cost membership drives frequency and locks in the most valuable cohort. | W60: Joins; buys more often. | X60: Neutral | Y60: + | Z60: Med | AA60: Neutral | AB60: Y | AC60: 0.05 | AD60: N | AE60: Membership module | AF60: Hard | AG60: 15-30 Days | AH60: 3 | AI60: 2 | AJ60: 2 | AK60: 2 | AL60: 3 | AM60: =ROUND(AH60*AI60*AJ60*AK60*AL60/3125*100,1) | AN60: Membership pilot to repeat cohort | AO60: Member repeat rate, LTV | AP60: Margin, free-ship cost | AQ60: Unassigned | AR60: Backlog

Sheet 3. Launch This Week
A1: LAUNCH THIS WEEK -> hand directly to the revenue team
A2: The 15 highest-priority interventions that can realistically go live within 7 days. Tactical & specific.
A3: Rank | B3: Initiative | C3: Exact Action | D3: Target Segment | E3: Category / SKU | F3: Offer / Mechanic | G3: Placement | H3: Required Assets | I3: Required Tech | J3: Owner | K3: Time to Launch | L3: Exp. Revenue Impact | M3: Margin Risk | N3: Measurement Plan | O3: Go / Test / Hold
A4: 1 | B4: Phone Case Attach Engine (screen guard + charm + strap) | C4: On every phone-case PDP + cart, show a 'Complete your case' rail: matching tempered-glass screen guard, MagSafe charm/grip and lanyard at 30-50% off ONLY when added with the case. Auto-apply in cart. | D4: All case buyers | E4: Phone Cases / 1101,1103,1815,1812 | F4: 30-50% off attach items with a case | G4: PDP below CTA + Cart FBT rail | H4: Copy + creative + PDP/cart slots | I4: Merch rule / FBT widget | J4: Unassigned | K4: 4-7 Days | L4: High | M4: Low | N4: +Rs AOV & UPT on case orders | O4: Go
A5: 2 | B5: Cart & checkout abandonment flow (email+SMS+push) | C5: 3-step abandonment series: 30min reminder, 24h with social proof, 48h with a modest incentive/free-ship reminder. Trigger separately for ATC-abandon vs checkout-abandon. | D5: Abandoners | E5: Cross-category / all | F5: Reminder; light incentive on step 3 | G5: Email/SMS/Push | H5: Copy + creative + PDP/cart slots | I5: CRM/ESP flows + events | J5: Unassigned | K5: 4-7 Days | L5: High | M5: Low | N5: Recovered revenue per abandoner | O5: Go
A6: 3 | B6: Cart low-price add-on rail (impulse SKUs) | C6: In cart, show a horizontal 'Add for a little more' rail of high-margin impulse SKUs <Rs499 (cable binds, screen guards, grips, coasters, charms) one-tap add. | D6: All carts | E6: Impulse tech / 1811,1812,1815,1705 | F6: No discount - convenience placement | G6: Cart add-on rail | H6: Copy + creative + PDP/cart slots | I6: Cart widget | J6: Unassigned | K6: 4-7 Days | L6: Med | M6: Low | N6: Attach rate of add-on SKUs | O6: Go
A7: 4 | B7: Bestseller & high-margin SKU prioritisation on PLP/home | C7: Re-sort PLPs and homepage rails to lead with proven high-CVR, high-margin bestsellers (Wrap-Lock cable, Orbis sling, Valet tray, Loop power banks, top case models); pin 'Bestseller' badges. | D7: All browsers | E7: Cross-category / bestsellers | F7: None | G7: PLP sort + homepage | H7: Copy + creative + PDP/cart slots | I7: Merch sort rules | J7: Unassigned | K7: Same Day | L7: Med | M7: Low | N7: PLP CVR, RPV | O7: Go
A8: 5 | B8: Prepaid free-shipping + Rs79 COD-fee reframing | C8: Make free shipping explicit and prepaid-gated with a visible bar ('You're Rs X from free shipping - pay online'); show the Rs79 COD fee as a saveable line at checkout with a one-tap 'Switch to UPI & save Rs79 + free ship'. | D8: COD-inclined shoppers | E8: Cross-category / all | F8: Free ship + waive COD fee on prepaid | G8: Cart + Checkout | H8: Copy + creative + PDP/cart slots | I8: Checkout config | J8: Unassigned | K8: 4-7 Days | L8: High | M8: Low | N8: Prepaid share, checkout completion | O8: Go
A9: 6 | B9: Power Bank + MagSafe Case cross-sell bundle | C9: On Loop Qi2 power-bank PDPs, add 'Powers up perfectly with' a MagSafe case at bundle price = power bank + case -10%. Reverse: on MagSafe case PDPs surface Loop power bank. | D9: Power-bank & MagSafe shoppers | E9: Power Banks / 1809,1103 | F9: Bundle -10% vs buying separately | G9: PDP FBT + Cart | H9: Copy + creative + PDP/cart slots | I9: FBT widget | J9: Unassigned | K9: 4-7 Days | L9: High | M9: Low | N9: Attach rate power bank<->case | O9: Go
A10: 7 | B10: Watch-band multi-pack ('Band Wardrobe') | C10: On Apple Watch band PDPs offer buy-2-save-15% / buy-3-save-20% across bands (mix leather/sport/nylon). 'Build your band wardrobe' selector. | D10: Watch-band shoppers | E10: Apple Watch Bands / 1801 | F10: Buy 2 -15%, 3+ -20% | G10: PDP selector + PLP banner | H10: Copy + creative + PDP/cart slots | I10: Qty-tier promo | J10: Unassigned | K10: 4-7 Days | L10: Med-High | M10: Low | N10: UPT on band orders | O10: Go
A11: 8 | B11: Reviews & UGC amplification on high-traffic PDPs | C11: Surface photo reviews, review count and Q&A prominently on top PDPs; seed Q&A for compatibility questions (fits which phone) to cut pre-purchase doubt. | D11: PDP visitors | E11: Cross-category / top PDPs | F11: None | G11: PDP | H11: Copy + creative + PDP/cart slots | I11: Reviews widget | J11: Unassigned | K11: 4-7 Days | L11: Med | M11: Low | N11: PDP CVR | O11: Go
A12: 9 | B12: Prepaid-only deeper offer to convert COD share | C12: Offer the best price/gift ONLY on prepaid (COD gets base price); reframe as 'prepaid perks' not a COD penalty. Protects margin via RTO reduction. | D12: COD-preferring | E12: Cross-category / all | F12: Prepaid-only extra 5% / gift | G12: Checkout | H12: Copy + creative + PDP/cart slots | I12: Checkout rules | J12: Unassigned | K12: 4-7 Days | L12: Med | M12: Low | N12: Prepaid share, contribution/order | O12: Go
A13: 10 | B13: Second-order accelerator coupon on thank-you + email | C13: Give every first-time buyer a time-boxed next-order incentive (e.g. Rs200 off next order within 30 days, min Rs1,499) on the thank-you page and in the order-confirmation email/SMS. | D13: First-order buyers | E13: Cross-category / all | F13: Rs200 off next order in 30 days (min Rs1,499) | G13: Thank-you + email/SMS | H13: Copy + creative + PDP/cart slots | I13: Coupon + CRM flow | J13: Unassigned | K13: 4-7 Days | L13: High | M13: Med | N13: 30/60-day repeat rate | O13: Test
A14: 11 | B14: First-order offer clarity + email/phone capture popup | C14: Tighten the welcome popup: 'Get Rs300 off your first order over Rs2,299 - unlock now' with email+phone capture, then persist the code in a sticky bar. Route to a first-time-buyer LP. | D14: New visitors | E14: Cross-category / all | F14: WELCOME300 (Rs300 off > Rs2,299) | G14: Popup + sticky bar + LP | H14: Copy + creative + PDP/cart slots | I14: Popup + CRM | J14: Unassigned | K14: 4-7 Days | L14: Med-High | M14: Med | N14: Capture rate, new-user CVR | O14: Test
A15: 12 | B15: Return/exchange-friendly messaging to unlock high-consideration bags | C15: Add prominent easy-returns + warranty + '30-day trial' style reassurance on backpack/luggage/premium-bag PDPs; show real reviews & durability proof. | D15: Bag shoppers | E15: Backpacks / 1201,1202 | F15: Trial/returns reassurance | G15: Bag PDPs | H15: Copy + creative + PDP/cart slots | I15: PDP content + returns policy | J15: Unassigned | K15: 4-7 Days | L15: Med | M15: Low | N15: Bag CVR | O15: Go
... A18: 15 | B18: Bank/UPI offer strip surfaced across funnel | C18: Surface live bank/UPI/cashback offers (HDFC SmartBuy, UPI cashback) as a strip on PDP/cart/checkout with 'view all offers' - reduce reliance on brand discounts. | D18: Deal-sensitive | E18: Cross-category / all | F18: Bank/UPI cashback (funded by partners) | G18: PDP/Cart/Checkout | H18: Copy + creative + PDP/cart slots | I18: Offers strip | J18: Unassigned | K18: 4-7 Days | L18: Med | M18: Low | N18: CVR, prepaid share | O18: Test

Sheet 4. D2C Brand Tactic DB
A1: D2C BRAND TACTIC DATABASE
A2: Real tactics from India & international D2C brands. Status = 'Reported' (search-index snippets; egress blocked live sites) - re-verify prices/thresholds before publishing.
A3: Brand | B3: Country | C3: Category | D3: Tactic Category | E3: Exact Mechanic | F3: Customer Proposition / Why It Works | G3: Objective (CVR/AOV/Freq) | H3: Applicability to DailyObjects | I3: DO Category | J3: Source URL | K3: Confidence | L3: Observed?
A4: boAt | B4: India | C4: Audio/Tech | D4: Payment (prepaid) | E4: Code BOATHEAD = flat extra 5% off ALL prepaid orders on top of sale | F4: Frames paying online as 'save more'; cuts RTO | G4: CVR+Margin | H4: Sitewide prepaid nudge; cases/power banks | I4: (map to DO) | J4: grabon.in/boat-coupons | K4: Med | L4: Reported
A5: boAt | B5: India | C5: Audio/Tech | D5: Payment (UPI) | E5: Flash extra 15% off on UPI + up to Rs150 cashback via PhonePe/GPay; stacks with bank offers | F5: Layered discounts feel like a treasure hunt; instant prepaid | G5: CVR | H5: Payday UPI cashback windows | I5: (map to DO) | J5: grabon.in/boat-coupons | K5: Med | L5: Reported
A6: boAt | B6: India | C6: Audio/Tech | D6: Launch anchoring | E6: New SKU launched at '55% off Rs19,999 RRP -> Rs8,999 for first customers' | F6: Introductory RRP anchor makes new SKU feel a steal | G6: CVR | H6: Loop/Surge launch pricing | I6: (map to DO) | J6: notebookcheck.net | K6: Med | L6: Reported
A7: boAt | B7: India | C7: Audio/Tech | D7: Gift-card discount | E7: E-gift card = instant flat 8% off | F7: Prepaid float + self-gifting locks spend | G7: Frequency | H7: Gift-card / prepaid credit | I7: (map to DO) | J7: gopaisa.com/boat | K7: Med | L7: Reported
A8: Noise | B8: India | C8: Wearables | D8: Bundle / cross-sell | E8: Smartwatch + TWS combo SKU at price below sum | F8: Two-device starter kit lifts basket in one click | G8: AOV | H8: Case + charger / band + charger combo | I8: (map to DO) | J8: gonoise.com | K8: Med | L8: Reported
A9: Noise | B9: India | C9: Wearables | D9: Multi-buy tier | E9: FEST15=15% off buy 2; FEST20=20% off buy 3+ | F9: Explicit ladder rewards adding a 3rd item | G9: AOV | H9: Buy-2/3 cases ladder | I9: (map to DO) | J9: gonoise.com | K9: Med | L9: Reported
A10: Noise | B10: India | C10: Wearables | D10: Free shipping | E10: Free shipping ALL orders, no minimum | F10: Removes friction on low-ticket | G10: CVR | H10: Prepaid free-ship framing | I10: (map to DO) | J10: gonoise.com | K10: Med | L10: Reported
A11: Boult | B11: India | C11: Audio | D11: Payment | E11: Rs100 instant cashback on prepaid; extra 5% UPI | F11: Cash incentive to prepay small ticket | G11: CVR | H11: Prepaid cashback | I11: (map to DO) | J11: grabon.in/boult-audio | K11: Med | L11: Reported
A12: Mokobara | B12: India | C12: Luggage/Bags | D12: Paid membership | E12: Moko Club Rs499/6mo = extra 5% off + 100-day trial + priority access | F12: Sunk-cost membership drives repeat on high ticket | G12: Frequency+AOV | H12: Paid membership for bags buyers | I12: (map to DO) | J12: grabon.in/mokobara | K12: Med | L12: Reported
A13: Mokobara | B13: India | C13: Luggage/Bags | D13: Risk reversal | E13: 30-day trial + 6-year warranty | F13: Kills 'is it worth it' objection on premium | G13: CVR | H13: Backpack/luggage trial + warranty | I13: (map to DO) | J13: grabon.in/mokobara | K13: Med | L13: Reported
A14: Mokobara | B14: India | C14: Luggage/Bags | D14: Set pricing | E14: Luggage 'sets' & travel combos at reduced set price | F14: Set aspiration + AOV | G14: AOV | H14: Bag + organiser + sleeve set | I14: (map to DO) | J14: mokobara.com/collections/explore-iconic-luggage | K14: Med | L14: Reported
... A54: Sugar/Nykaa | B54: India | C54: Beauty | D54: Sample/mini ladder | E54: Add mini/sample as low-price add-on near free-ship bar | F54: Cheap trial closes the gap + trials new lines | G54: AOV | H54: Low-price add-on rail in cart | I54: (map to DO) | J54: nykaa.com (observed pattern) | K54: Med | L54: Reported

Sheet 5. Category Opportunity Map
A1: CATEGORY OPPORTUNITY MAP
A2: GA4 item metrics = OBSERVED; cid->name mapping = INFERRED from site URL taxonomy. ASP is item-level (not order AOV). 2025-08-01 to 2026-07-31
A3: cid | B3: Category (INF name) | C3: Category Role | D3: Item Revenue (Rs) | E3: Units Sold | F3: Item ASP (Rs) | G3: Item Views | H3: ATC Rate | I3: View->Purchase | J3: Price Range | K3: Purchase Behaviour | L3: Primary Problem | M3: Primary Revenue Opportunity | N3: Best Offer Mechanic | O3: Best Bundle | P3: Best Cross-Sell | Q3: Best CRM Opportunity | R3: Best Merchandising | S3: Recommended Immediate Action | T3: Priority
A4: 1809 | B4: Power Banks & Wireless Power | C4: Hero / Destination | D4: 3.9724405e+08 | E4: 127803 | F4: =IF(E4=0,0,D4/E4) | G4: 9234794 | H4: =IF(G4=0,0,647279/G4) | I4: =IF(G4=0,0,E4/G4) | J4: Rs4,999-8,499 | K4: Considered, high ASP | L4: Hero revenue driver but low ATC (7%) | M4: Bundle with MagSafe case; cross-sell cable; launch attach | N4: Bundle -10% + launch kit | O4: Power bank + MagSafe case | P4: + Cable/adapter | Q4: Restock/price-drop alerts on Loop | R4: Lead homepage + device hub | S4: Ship power-bank+case bundle on Loop PDPs (ID02) | T4: High
A5: 1101 | B5: Phone Cases (core) | C5: Hero / Destination | D5: 3.290038e+08 | E5: 307976 | F5: =IF(E5=0,0,D5/E5) | G5: 25760937 | H5: =IF(G5=0,0,2408681/G5) | I5: =IF(G5=0,0,E5/G5) | J5: Rs899-2,399 | K5: Massive traffic, low ASP entry | L5: 57% of item views convert at 1.2% & ASP only ~Rs1,068 | M5: Attach screen guard/charm/grip; tier upsell; quiz | N5: Attach 30-50% off with case | O5: Case + screen guard + grip | P5: Screen guard | Q5: BIS on new phone models; replacement cycle | R5: Lead nav + shop-by-device | S5: Launch case attach engine + tier upsell (ID01/ID16) | T5: High
A6: 1801 | B6: Apple Watch Bands | C6: Ecosystem / Repeat | D6: 1.1879657e+08 | E6: 107273 | F6: =IF(E6=0,0,D6/E6) | G6: 7095030 | H6: =IF(G6=0,0,490322/G6) | I6: =IF(G6=0,0,E6/G6) | J6: Rs1,299-2,499 | K6: Fashion rotation, repeat | L6: Bought singly; multi-band potential untapped | M6: Multi-band buy-2/3 escalator | N6: Buy 2 -15% | O6: Band wardrobe | P6: Watch charger/stand | Q6: Seasonal band drops to owners | R6: Watch hub | S6: Multi-band escalator on band PDPs (ID04) | T6: High
A7: 1703 | B7: Tech / Cable Organisers | C7: Add-on / Cross-sell | D7: 93174478 | E7: 82770 | F7: =IF(E7=0,0,D7/E7) | G7: 4325738 | H7: =IF(G7=0,0,344260/G7) | I7: =IF(G7=0,0,E7/G7) | J7: Rs499-1,999 | K7: Strong attach category | L7: Under-attached to bags/power banks | M7: Attach to bag/power-bank; hero GWP | N7: Free GWP at mid rung | O7: Bag/power bank -> organiser | P7: Cables | Q7: Cross-cat intro to case buyers | R7: Attach rails everywhere | S7: Use as hero GWP + bag attach (ID03/ID46) | T7: High
A8: 1201 | B8: Backpacks | C8: High-consideration | D8: 77009769 | E8: 39702 | F8: =IF(E8=0,0,D8/E8) | G8: 5171423 | H8: =IF(G8=0,0,191289/G8) | I8: =IF(G8=0,0,E8/G8) | J8: Rs1,349-3,000+ | K8: High-consideration, hesitant | L8: Lowest view->purchase (0.77%) & ATC (3.7%) | M8: Risk reversal + carry-system bundle | N8: Kit -12% + trial/returns | O8: Bag + sleeve + organiser | P8: Laptop sleeve | Q8: Winback + wishlist for considered buyers | R8: Use-case hub (back-to-office/travel) | S8: Add risk-reversal + carry-system bundle (ID03/ID39) | T8: High
A9: 1702 | B9: Desk Organisers & Trays | C9: Add-on / Impulse | D9: 58528287 | E9: 44126 | F9: =IF(E9=0,0,D9/E9) | G9: 1716262 | H9: =IF(G9=0,0,158526/G9) | I9: =IF(G9=0,0,E9/G9) | J9: Rs799-2,499 | K9: Impulse + gifting | L9: Under-merchandised despite intent | M9: Desk-setup bundle | N9: Setup kit -12% | O9: Desk mat + organiser + tray | P9: Coaster/cable mgmt | Q9: Desk refresh CRM | R9: Shop-the-look | S9: Desk-setup complete-the-look bundle (ID10) | T9: High
A10: 1204 | B10: Laptop Sleeves | C10: Accessory / Attach | D10: 57414516 | E10: 24665 | F10: =IF(E10=0,0,D10/E10) | G10: 2992044 | H10: =IF(G10=0,0,118860/G10) | I10: =IF(G10=0,0,E10/G10) | J10: Rs900-1,800 | K10: Attach to bags/laptops | L10: Sold solo; natural bag attach | M10: Attach to backpack/laptop bag | N10: Kit with bag | O10: Bag + sleeve | P10: Tech organiser | Q10: Attach in bag flows | R10: Carry-system module | S10: Bundle into carry system (ID03) | T10: High
A11: 1103 | B11: Phone Cases (MagSafe/premium) | C11: Hero / Destination | D11: 55615165 | E11: 42193 | F11: =IF(E11=0,0,D11/E11) | G11: 3209429 | H11: =IF(G11=0,0,174079/G11) | I11: =IF(G11=0,0,E11/G11) | J11: Rs999-2,399 | K11: Premium case tier | L11: Higher ASP than clear cases | M11: Tier upsell + MagSafe bundle | N11: Upgrade toggle | O11: MagSafe case + power bank | P11: Screen guard | Q11: Ecosystem cross-sell | R11: Device hub premium tier | S11: Default recommend mid tier (ID16) | T11: High
A12: 1202 | B12: Premium Bags / Luggage | C12: High-consideration | D12: 49972854 | E12: 13378 | F12: =IF(E12=0,0,D12/E12) | G12: 2157624 | H12: =IF(G12=0,0,61983/G12) | I12: =IF(G12=0,0,E12/G12) | J12: Rs2,000-4,000+ | K12: Premium/luggage, highest ASP | L12: High ASP, low volume, considered | M12: Risk reversal + set pricing | N12: Set pricing | O12: Luggage set + organiser | P12: Packing organiser | Q12: VIP/high-AOV nurture | R12: Premium carry hub | S12: Set pricing + trial reassurance (ID39/ID03) | T12: Med
A13: 1805 | B13: Chargers & Adapters | C13: Ecosystem / Replace | D13: 46914557 | E13: 23368 | F13: =IF(E13=0,0,D13/E13) | G13: 2606672 | H13: =IF(G13=0,0,146025/G13) | I13: =IF(G13=0,0,E13/G13) | J13: Rs999-6,499 | K13: Ecosystem/replacement | L13: Chargers attach to phone/power ecosystem | M13: Attach to case/power bank | N13: Bundle | O13: Charger + cable | P13: Cable | Q13: Replacement reminders | R13: Device hub | S13: Attach to MagSafe/device ecosystem (ID02/ID33) | T13: Med
A14: 1203 | B14: Crossbody / Sling Bags | C14: High-consideration | D14: 43188218 | E14: 30156 | F14: =IF(E14=0,0,D14/E14) | G14: 3038751 | H14: =IF(G14=0,0,132325/G14) | I14: =IF(G14=0,0,E14/G14) | J14: Rs1,249-2,499 | K14: Fashion carry, women-led | L14: Solid volume; attach weak | M14: Cross-sell wallet/organiser | N14: Combo | O14: Sling + wallet | P14: Card holder | Q14: Style drops CRM | R14: Shop-by-style | S14: Sling + wallet combo (Zouk-style) (ID45) | T14: Med
A15: 1102 | B15: Phone Cases (clear/hybrid) | C15: Hero / Destination | D15: 26614245 | E15: 14905 | F15: =IF(E15=0,0,D15/E15) | G15: 1219444 | H15: =IF(G15=0,0,47938/G15) | I15: =IF(G15=0,0,E15/G15) | J15: varies | K15: See role | L15: Under-activated vs traffic | M15: Attach + CRM | N15: GWP/attach | O15: Complementary item | P15: Adjacent accy | Q15: Lifecycle CRM | R15: Merchandise in hub | S15: Attach + surface in relevant hub | T15: Med
A16: 1701 | B16: Desk Mats & Pads | C16: Add-on / Impulse | D16: 21554349 | E16: 22657 | F16: =IF(E16=0,0,D16/E16) | G16: 507203 | H16: =IF(G16=0,0,104953/G16) | I16: =IF(G16=0,0,E16/G16) | J16: varies | K16: See role | L16: Under-activated vs traffic | M16: Attach + CRM | N16: GWP/attach | O16: Complementary item | P16: Adjacent accy | Q16: Lifecycle CRM | R16: Merchandise in hub | S16: Attach + surface in relevant hub | T16: Med
A17: 1811 | B17: Cables & Charging Accy | C17: Impulse / Attach | D17: 19283567 | E17: 13335 | F17: =IF(E17=0,0,D17/E17) | G17: 1250037 | H17: =IF(G17=0,0,59003/G17) | I17: =IF(G17=0,0,E17/G17) | J17: varies | K17: See role | L17: Under-activated vs traffic | M17: Attach + CRM | N17: GWP/attach | O17: Complementary item | P17: Adjacent accy | Q17: Lifecycle CRM | R17: Merchandise in hub | S17: Attach + surface in relevant hub | T17: Med
A18: 1104 | B18: Phone Cases (custom/artist) | C18: Hero / Destination | D18: 15387327 | E18: 16713 | F18: =IF(E18=0,0,D18/E18) | G18: 807172 | H18: =IF(G18=0,0,59770/G18) | I18: =IF(G18=0,0,E18/G18) | J18: varies | K18: See role | L18: Under-activated vs traffic | M18: Attach + CRM | N18: GWP/attach | O18: Complementary item | P18: Adjacent accy | Q18: Lifecycle CRM | R18: Merchandise in hub | S18: Attach + surface in relevant hub | T18: Med
A19: 1814 | B19: Tech Accy (stands/mounts) | C19: Impulse / Attach | D19: 14987157 | E19: 11513 | F19: =IF(E19=0,0,D19/E19) | G19: 366384 | H19: =IF(G19=0,0,109794/G19) | I19: =IF(G19=0,0,E19/G19) | J19: varies | K19: See role | L19: Under-activated vs traffic | M19: Attach + CRM | N19: GWP/attach | O19: Complementary item | P19: Adjacent accy | Q19: Lifecycle CRM | R19: Merchandise in hub | S19: Attach + surface in relevant hub | T19: Low
A20: 1813 | B20: Tech Accy (misc) | C20: Impulse / Attach | D20: 13650558 | E20: 14562 | F20: =IF(E20=0,0,D20/E20) | G20: 796233 | H20: =IF(G20=0,0,85938/G20) | I20: =IF(G20=0,0,E20/G20) | J20: varies | K20: See role | L20: Under-activated vs traffic | M20: Attach + CRM | N20: GWP/attach | O20: Complementary item | P20: Adjacent accy | Q20: Lifecycle CRM | R20: Merchandise in hub | S20: Attach + surface in relevant hub | T20: Low
A21: 1205 | B21: Tote Bags | C21: Accessory / Add-on | D21: 11023656 | E21: 3200 | F21: =IF(E21=0,0,D21/E21) | G21: 550150 | H21: =IF(G21=0,0,18340/G21) | I21: =IF(G21=0,0,E21/G21) | J21: varies | K21: See role | L21: Under-activated vs traffic | M21: Attach + CRM | N21: GWP/attach | O21: Complementary item | P21: Adjacent accy | Q21: Lifecycle CRM | R21: Merchandise in hub | S21: Attach + surface in relevant hub | T21: Low
A22: 1301 | B22: Wallets (bifold/leather) | C22: Gifting / Repeat | D22: 9770788 | E22: 12072 | F22: =IF(E22=0,0,D22/E22) | G22: 658364 | H22: =IF(G22=0,0,47019/G22) | I22: =IF(G22=0,0,E22/G22) | J22: varies | K22: See role | L22: Under-activated vs traffic | M22: Attach + CRM | N22: GWP/attach | O22: Complementary item | P22: Adjacent accy | Q22: Lifecycle CRM | R22: Merchandise in hub | S22: Attach + surface in relevant hub | T22: Low
A23: 1812 | B23: Tech Accy (grips/rings) | C23: Impulse / Attach | D23: 6648714 | E23: 10586 | F23: =IF(E23=0,0,D23/E23) | G23: 132387 | H23: =IF(G23=0,0,38819/G23) | I23: =IF(G23=0,0,E23/G23) | J23: varies | K23: See role | L23: Under-activated vs traffic | M23: Attach + CRM | N23: GWP/attach | O23: Complementary item | P23: Adjacent accy | Q23: Lifecycle CRM | R23: Merchandise in hub | S23: Attach + surface in relevant hub | T23: Low
A24: 1304 | B24: Card Holders / Slim Wallets | C24: Gifting / Impulse | D24: 5764217 | E24: 6883 | F24: =IF(E24=0,0,D24/E24) | G24: 635184 | H24: =IF(G24=0,0,31044/G24) | I24: =IF(G24=0,0,E24/G24) | J24: varies | K24: See role | L24: Under-activated vs traffic | M24: Attach + CRM | N24: GWP/attach | O24: Complementary item | P24: Adjacent accy | Q24: Lifecycle CRM | R24: Merchandise in hub | S24: Attach + surface in relevant hub | T24: Low
A25: 1815 | B25: Tech Accy (screen guards) | C25: Attach / Replace | D25: 5479024 | E25: 7176 | F25: =IF(E25=0,0,D25/E25) | G25: 115872 | H25: =IF(G25=0,0,47517/G25) | I25: =IF(G25=0,0,E25/G25) | J25: varies | K25: See role | L25: Under-activated vs traffic | M25: Attach + CRM | N25: GWP/attach | O25: Complementary item | P25: Adjacent accy | Q25: Lifecycle CRM | R25: Merchandise in hub | S25: Attach + surface in relevant hub | T25: Low
A26: 1402 | B26: AirPods Cases | C26: Impulse / Attach | D26: 5012482 | E26: 13056 | F26: =IF(E26=0,0,D26/E26) | G26: 301454 | H26: =IF(G26=0,0,41307/G26) | I26: =IF(G26=0,0,E26/G26) | J26: varies | K26: See role | L26: Under-activated vs traffic | M26: Attach + CRM | N26: GWP/attach | O26: Complementary item | P26: Adjacent accy | Q26: Lifecycle CRM | R26: Merchandise in hub | S26: Attach + surface in relevant hub | T26: Low
A27: 1403 | B27: AirPods Pro Cases | C27: Impulse / Attach | D27: 4385984 | E27: 4416 | F27: =IF(E27=0,0,D27/E27) | G27: 246992 | H27: =IF(G27=0,0,14093/G27) | I27: =IF(G27=0,0,E27/G27) | J27: varies | K27: See role | L27: Under-activated vs traffic | M27: Attach + CRM | N27: GWP/attach | O27: Complementary item | P27: Adjacent accy | Q27: Lifecycle CRM | R27: Merchandise in hub | S27: Attach + surface in relevant hub | T27: Low
A28: 1302 | B28: Wallets (zip/travel) | C28: Gifting / Repeat | D28: 4321887 | E28: 7379 | F28: =IF(E28=0,0,D28/E28) | G28: 554915 | H28: =IF(G28=0,0,34390/G28) | I28: =IF(G28=0,0,E28/G28) | J28: varies | K28: See role | L28: Under-activated vs traffic | M28: Attach + CRM | N28: GWP/attach | O28: Complementary item | P28: Adjacent accy | Q28: Lifecycle CRM | R28: Merchandise in hub | S28: Attach + surface in relevant hub | T28: Low
A29: 1307 | B29: Wallets (money clip/misc) | C29: Gifting / Impulse | D29: 3668524 | E29: 5790 | F29: =IF(E29=0,0,D29/E29) | G29: 381418 | H29: =IF(G29=0,0,28130/G29) | I29: =IF(G29=0,0,E29/G29) | J29: varies | K29: See role | L29: Under-activated vs traffic | M29: Attach + CRM | N29: GWP/attach | O29: Complementary item | P29: Adjacent accy | Q29: Lifecycle CRM | R29: Merchandise in hub | S29: Attach + surface in relevant hub | T29: Low
A30: 1207 | B30: Bags (misc / laptop bags) | C30: Accessory / Attach | D30: 2926530 | E30: 5920 | F30: =IF(E30=0,0,D30/E30) | G30: 352841 | H30: =IF(G30=0,0,25588/G30) | I30: =IF(G30=0,0,E30/G30) | J30: varies | K30: See role | L30: Under-activated vs traffic | M30: Attach + CRM | N30: GWP/attach | O30: Complementary item | P30: Adjacent accy | Q30: Lifecycle CRM | R30: Merchandise in hub | S30: Attach + surface in relevant hub | T30: Low
A31: 1305 | B31: Wallets for Men | C31: Gifting / Repeat | D31: 2838951 | E31: 2666 | F31: =IF(E31=0,0,D31/E31) | G31: 174026 | H31: =IF(G31=0,0,10788/G31) | I31: =IF(G31=0,0,E31/G31) | J31: varies | K31: See role | L31: Under-activated vs traffic | M31: Attach + CRM | N31: GWP/attach | O31: Complementary item | P31: Adjacent accy | Q31: Lifecycle CRM | R31: Merchandise in hub | S31: Attach + surface in relevant hub | T31: Low
A32: 1705 | B32: Drinkware / Coasters | C32: Impulse / Gifting | D32: 2532741 | E32: 3259 | F32: =IF(E32=0,0,D32/E32) | G32: 242071 | H32: =IF(G32=0,0,10985/G32) | I32: =IF(G32=0,0,E32/G32) | J32: varies | K32: See role | L32: Under-activated vs traffic | M32: Attach + CRM | N32: GWP/attach | O32: Complementary item | P32: Adjacent accy | Q32: Lifecycle CRM | R32: Merchandise in hub | S32: Attach + surface in relevant hub | T32: Low
A33: 1401 | B33: AirPods (misc) | C33: Impulse / Attach | D33: 1887587 | E33: 2163 | F33: =IF(E33=0,0,D33/E33) | G33: 95051 | H33: =IF(G33=0,0,7185/G33) | I33: =IF(G33=0,0,E33/G33) | J33: varies | K33: See role | L33: Under-activated vs traffic | M33: Attach + CRM | N33: GWP/attach | O33: Complementary item | P33: Adjacent accy | Q33: Lifecycle CRM | R33: Merchandise in hub | S33: Attach + surface in relevant hub | T33: Low
A34: 1303 | B34: Wallets (passport) | C34: Gifting / Low-freq | D34: 1477440 | E34: 1566 | F34: =IF(E34=0,0,D34/E34) | G34: 79578 | H34: =IF(G34=0,0,5326/G34) | I34: =IF(G34=0,0,E34/G34) | J34: varies | K34: See role | L34: Under-activated vs traffic | M34: Attach + CRM | N34: GWP/attach | O34: Complementary item | P34: Adjacent accy | Q34: Lifecycle CRM | R34: Merchandise in hub | S34: Attach + surface in relevant hub | T34: Low
A35: 1604 | B35: Gift Sets / Bundles | C35: Gifting | D35: 1113000 | E35: 490 | F35: =IF(E35=0,0,D35/E35) | G35: 33381 | H35: =IF(G35=0,0,2195/G35) | I35: =IF(G35=0,0,E35/G35) | J35: varies | K35: See role | L35: Under-activated vs traffic | M35: Attach + CRM | N35: GWP/attach | O35: Complementary item | P35: Adjacent accy | Q35: Lifecycle CRM | R35: Merchandise in hub | S35: Attach + surface in relevant hub | T35: Low
A36: 1602 | B36: Gift Cards | C36: Gifting | D36: 1084610 | E36: 290 | F36: =IF(E36=0,0,D36/E36) | G36: 22852 | H36: =IF(G36=0,0,537/G36) | I36: =IF(G36=0,0,E36/G36) | J36: varies | K36: See role | L36: Under-activated vs traffic | M36: Attach + CRM | N36: GWP/attach | O36: Complementary item | P36: Adjacent accy | Q36: Lifecycle CRM | R36: Merchandise in hub | S36: Attach + surface in relevant hub | T36: Low
A37: 1603 | B37: Gifting (corporate/curated) | C37: Gifting | D37: 1004492 | E37: 308 | F37: =IF(E37=0,0,D37/E37) | G37: 66359 | H37: =IF(G37=0,0,1135/G37) | I37: =IF(G37=0,0,E37/G37) | J37: varies | K37: See role | L37: Under-activated vs traffic | M37: Attach + CRM | N37: GWP/attach | O37: Complementary item | P37: Adjacent accy | Q37: Lifecycle CRM | R37: Merchandise in hub | S37: Attach + surface in relevant hub | T37: Low
A38: 1707 | B38: Drinkware (bottles/flasks) | C38: Impulse / Gifting | D38: 881169 | E38: 1001 | F38: =IF(E38=0,0,D38/E38) | G38: 75861 | H38: =IF(G38=0,0,4155/G38) | I38: =IF(G38=0,0,E38/G38) | J38: varies | K38: See role | L38: Under-activated vs traffic | M38: Attach + CRM | N38: GWP/attach | O38: Complementary item | P38: Adjacent accy | Q38: Lifecycle CRM | R38: Merchandise in hub | S38: Attach + surface in relevant hub | T38: Low
B39: TOTAL | D39: =SUM(D4:D38) | E39: =SUM(E4:E38) | G39: =SUM(G4:G38)

Sheet 6. Basket Affinity
A1: BASKET AFFINITY & TOP-20 BUNDLE OPPORTUNITIES
A2: Attach rate & lift are HYPOTHESES (no order-line SKU data available; GA4 provides no true co-purchase). Validate with a market-basket run on order-line data, then bundle. Combined ASP & saving are formula-driven.
A3: Rank | B3: Primary Product | C3: Primary Cat | D3: Secondary Product | E3: Secondary Cat | F3: Est. Attach Rate (HYP) | G3: Est. Lift (HYP) | H3: Primary ASP | I3: Secondary ASP | J3: Combined ASP | K3: Bundle Exists? | L3: Recommended Bundle Price | M3: Customer Saving | N3: Recommended Placement | O3: Priority (/100) | P3: Idea Ref
A4: 1 | B4: Phone Case | C4: 1101 | D4: Tempered Screen Guard | E4: 1815 | F4: 0.35 | G4: 4.2 | H4: 1068 | I4: 764 | J4: =H4+I4 | K4: None yet | L4: =ROUND(J4*0.9,0) | M4: =J4-L4 | N4: PDP FBT + Cart rail | O4: 100
A5: 2 | B5: MagSafe Case | C5: 1103 | D5: Screen Guard | E5: 1815 | F5: 0.33 | G5: 4 | H5: 1318 | I5: 764 | J5: =H5+I5 | K5: None yet | L5: =ROUND(J5*0.9,0) | M5: =J5-L5 | N5: PDP FBT + Cart rail | O5: 89.8
A6: 3 | B6: Desk Organiser | C6: 1702 | D6: Desk Mat | E6: 1701 | F6: 0.28 | G6: 3.4 | H6: 1326 | I6: 951 | J6: =H6+I6 | K6: None yet | L6: =ROUND(J6*0.9,0) | M6: =J6-L6 | N6: PDP FBT + Cart rail | O6: 64.8
A7: 4 | B7: Backpack | C7: 1201 | D7: Laptop Sleeve | E7: 1204 | F7: 0.2 | G7: 3.6 | H7: 1940 | I7: 2328 | J7: =H7+I7 | K7: Combo (ad hoc) | L7: =ROUND(J7*0.9,0) | M7: =J7-L7 | N7: PDP FBT + Cart rail | O7: 49
A8: 5 | B8: Desk Mat | C8: 1701 | D8: Cable Organiser | E8: 1703 | F8: 0.22 | G8: 2.9 | H8: 951 | I8: 1126 | J8: =H8+I8 | K8: None yet | L8: =ROUND(J8*0.9,0) | M8: =J8-L8 | N8: PDP FBT + Cart rail | O8: 43.4
A9: 6 | B9: Loop Power Bank | C9: 1809 | D9: Braided Cable | E9: 1811 | F9: 0.22 | G9: 2.8 | H9: 3108 | I9: 1446 | J9: =H9+I9 | K9: None yet | L9: =ROUND(J9*0.9,0) | M9: =J9-L9 | N9: PDP FBT + Cart rail | O9: 41.9
A10: 7 | B10: Premium Bag/Luggage | C10: 1202 | D10: Tech Organiser | E10: 1703 | F10: 0.18 | G10: 3.2 | H10: 3735 | I10: 1126 | J10: =H10+I10 | K10: None yet | L10: =ROUND(J10*0.9,0) | M10: =J10-L10 | N10: PDP FBT + Cart rail | O10: 39.2
A11: 8 | B11: Phone Case | C11: 1101 | D11: MagSafe Grip/Ring | E11: 1812 | F11: 0.18 | G11: 3.1 | H11: 1068 | I11: 628 | J11: =H11+I11 | K11: None yet | L11: =ROUND(J11*0.9,0) | M11: =J11-L11 | N11: PDP FBT + Cart rail | O11: 38
A12: 9 | B12: Apple Watch Band | C12: 1801 | D12: 2nd Watch Band | E12: 1801 | F12: 0.25 | G12: 2.2 | H12: 1107 | I12: 1107 | J12: =H12+I12 | K12: None yet | L12: =ROUND(J12*0.9,0) | M12: =J12-L12 | N12: PDP FBT + Cart rail | O12: 37.4
A13: 10 | B13: Laptop Sleeve | C13: 1204 | D13: Tech Organiser | E13: 1703 | F13: 0.19 | G13: 2.7 | H13: 2328 | I13: 1126 | J13: =H13+I13 | K13: None yet | L13: =ROUND(J13*0.9,0) | M13: =J13-L13 | N13: PDP FBT + Cart rail | O13: 34.9
A14: 11 | B14: Backpack | C14: 1201 | D14: Tech/Cable Organiser | E14: 1703 | F14: 0.16 | G14: 3 | H14: 1940 | I14: 1126 | J14: =H14+I14 | K14: None yet | L14: =ROUND(J14*0.9,0) | M14: =J14-L14 | N14: PDP FBT + Cart rail | O14: 32.7
A15: 12 | B15: Wallet | C15: 1301 | D15: Card Holder | E15: 1304 | F15: 0.17 | G15: 2.5 | H15: 809 | I15: 837 | J15: =H15+I15 | K15: None yet | L15: =ROUND(J15*0.9,0) | M15: =J15-L15 | N15: PDP FBT + Cart rail | O15: 28.9
... A23: 20 | B23: Phone Case | C23: 1101 | D23: AirPods Case | E23: 1402 | F23: 0.08 | G23: 1.7 | H23: 1068 | I23: 384 | J23: =H23+I23 | K23: None yet | L23: =ROUND(J23*0.9,0) | M23: =J23-L23 | N23: PDP FBT + Cart rail | O23: 9.3

Sheet 7. Cart Threshold Analysis
A1: CART THRESHOLD ANALYSIS
A2: Set free-gift / free-ship / spend-ladder thresholds from where baskets cluster. HYPOTHESIS distribution - the order-level file (daily-marketing-report-v2-2.csv, 32MB, item-level w/ Order Total/Discount/Payment/Coupon/New User) exceeds the 10MB data-fetch cap in this environment. To make this tab OBSERVED: split the CSV into <10MB parts (or run locally), aggregate Order Total (deduped by Order No.) into these bands, and overwrite the yellow %Orders cells. Yellow cells = editable inputs; totals & revenue are formula-driven.
A3: Basket Band | B3: % Orders (input) | C3: Est. Orders | D3: % Revenue | E3: Est. Revenue (Rs) | F3: Band Mid AOV | G3: Units/Order | H3: Current Offer | I3: Recommended Intervention | J3: Incremental Spend to Next Rung | K3: Proposed Gift / Benefit | L3: Est. Gift COGS (Rs) | M3: Potential AOV Uplift | N3: Priority
A4: Rs0-999 | B4: 0.14 | C4: =ROUND($B4*$C$15,0) | D4: =IF($E$14=0,0,E4/$E$14) | E4: =C4*F4 | F4: 600 | G4: - | H4: COD fee applies | I4: Add low-price add-on to cross Rs999; free-ship teaser | K4: - | L4: 0 | M4: +8-12% | N4: Med
A5: Rs1,000-1,499 | B5: 0.2 | C5: =ROUND($B5*$C$15,0) | D5: =IF($E$14=0,0,E5/$E$14) | E5: =C5*F5 | F5: 1250 | G5: - | H5: Free ship (prepaid) | I5: Nudge to Rs1,999 gift rung with attach rail | K5: Cable bind (Rs from ~40 COGS) | L5: 45 | M5: +6-10% | N5: High
A6: Rs1,500-1,999 | B6: 0.19 | C6: =ROUND($B6*$C$15,0) | D6: =IF($E$14=0,0,E6/$E$14) | E6: =C6*F6 | F6: 1750 | G6: - | H6: Free ship (prepaid) | I6: GWP rung: free cable bind at Rs1,999 | K6: Cable bind | L6: 45 | M6: +6-10% | N6: High
A7: Rs2,000-2,499 | B7: 0.15 | C7: =ROUND($B7*$C$15,0) | D7: =IF($E$14=0,0,E7/$E$14) | E7: =C7*F7 | F7: 2250 | G7: - | H7: Free ship (prepaid) | I7: WELCOME300 + free ship anchor here (new users) | K7: Free shipping + WELCOME300 | L7: 60 | M7: +5-8% | N7: High
A8: Rs2,500-2,999 | B8: 0.11 | C8: =ROUND($B8*$C$15,0) | D8: =IF($E$14=0,0,E8/$E$14) | E8: =C8*F8 | F8: 2750 | G8: - | H8: Free ship (prepaid) | I8: Mid GWP rung: free tech organiser at Rs2,499 | K8: Tech organiser (low COGS) | L8: 90 | M8: +5-8% | N8: High
A9: Rs3,000-3,499 | B9: 0.08 | C9: =ROUND($B9*$C$15,0) | D9: =IF($E$14=0,0,E9/$E$14) | E9: =C9*F9 | F9: 3250 | G9: - | H9: Free ship (prepaid) | I9: Spend-ladder 10% / choice-gift toward Rs2,999 | K9: Choice of gift | L9: 90 | M9: +4-7% | N9: Med
A10: Rs3,500-3,999 | B10: 0.05 | C10: =ROUND($B10*$C$15,0) | D10: =IF($E$14=0,0,E10/$E$14) | E10: =C10*F10 | F10: 3750 | G10: - | H10: Free ship (prepaid) | I10: Bundle upsell (case+power bank / carry system) | K10: Bundle saving | L10: 0 | M10: +3-5% | N10: Med
A11: Rs4,000-4,499 | B11: 0.03 | C11: =ROUND($B11*$C$15,0) | D11: =IF($E$14=0,0,E11/$E$14) | E11: =C11*F11 | F11: 4250 | G11: - | H11: Free ship (prepaid) | I11: Premium choice-gift at Rs3,999 | K11: Premium choice gift | L11: 150 | M11: +3-5% | N11: Med
A12: Rs4,500-4,999 | B12: 0.02 | C12: =ROUND($B12*$C$15,0) | D12: =IF($E$14=0,0,E12/$E$14) | E12: =C12*F12 | F12: 4750 | G12: - | H12: Free ship (prepaid) | I12: Concierge/gift-set upsell | K12: Gift packaging | L12: 60 | M12: +2-4% | N12: Low
A13: Rs5,000+ | B13: 0.03 | C13: =ROUND($B13*$C$15,0) | D13: =IF($E$14=0,0,E13/$E$14) | E13: =C13*F13 | F13: 6500 | G13: - | H13: Free ship (prepaid) | I13: VIP / high-AOV nurture; no discount needed | K13: Early access | L13: 0 | M13: - | N13: Low
A14: TOTAL / ASSUMPTION | B14: =SUM(B4:B13) | C14: =SUM(C4:C13) | E14: =SUM(E4:E13)
A15: Total annual web+app orders (input) | C15: 553257
A17: RECOMMENDED THRESHOLDS (tune to observed clustering):
A18: • Free shipping: prepaid, no minimum (or >= Rs999) - clarity beats a high bar
A19: • Free-gift ladder: Rs1,999 (cable bind) -> Rs2,999 (tech organiser / choice gift)
A20: • New-user first order: align WELCOME300 + gift + free ship at Rs2,299
A21: • Spend ladder (if used): 5% @ Rs1,999 / 10% @ Rs2,999 - cap depth, prepaid-gated

Sheet 8. Customer x Offer Engine
A1: CUSTOMER x OFFER DECISION ENGINE
A2: Who gets what. Do NOT treat every customer identically - segment by intent, value & history.
A3: # | B3: Customer Scenario | C3: New/Repeat | D3: Order Stage | E3: Traffic Source | F3: Category Viewed | G3: Cart Value / Size | H3: Current Behaviour | I3: Recommended Intervention | J3: Offer | K3: Threshold | L3: Message | M3: Channel | N3: Trigger | O3: Expected Behaviour | P3: Margin Risk | Q3: Priority
A4: 1 | B4: New Meta/IG visitor, Rs1,800 cart | C4: New | D4: O1 | E4: Paid Social | F4: Phone case | G4: Rs1,800 / 1-2 items | H4: Low CVR (0.38%), price-checking | I4: Attach rail + free-ship clarity + WELCOME300 progress | J4: Add screen guard 40% off; Rs300 off @ Rs2,299 | K4: Rs2,299 | L4: 'Add a screen guard - unlock Rs300 off + free shipping' | M4: On-site + cart | N4: ATC no checkout | O4: Adds guard, crosses Rs2,299 | P4: Med | Q4: High
A5: 2 | B5: Repeat customer, Rs4,200 cart | C5: Repeat | D5: O2+ | E5: Direct | F5: Power bank + case | G5: Rs4,200 / 2-3 items | H5: High intent, high value | I5: No discount - reward loyalty w/ points + premium GWP | J5: Points + choice-gift @ Rs3,999 | K5: Rs3,999 | L5: 'You've unlocked a free gift - pick yours' | M5: On-site + email | N5: Cart | O5: Completes, picks gift | P5: Low | Q5: High
A6: 3 | B6: Existing phone-case buyer browsing chargers | C6: Repeat | D6: O2 | E6: Email/Direct | F6: Chargers | G6: browsing | H6: Cross-category intent | I6: Cross-sell MagSafe charger + power bank bundle | J6: Bundle -10% | K6: - | L6: 'Complete your MagSafe setup' | M6: Email/On-site | N6: Browse power/chargers | O6: Buys charger/power bank | P6: Low | Q6: High
A7: 4 | B7: Dormant backpack customer (120d) | C7: Dormant | D7: O1/O2 | E7: CRM | F7: Bags (past) | G7: none | H7: Lapsed | I7: Winback w/ new drops + organiser attach | J7: Rs300 off > Rs1,999 | K7: Rs1,999 | L7: 'New carry drops + a little something for you' | M7: Email/SMS | N7: No purchase 90-180d | O7: Reactivates | P7: Med | Q7: Med
A8: 5 | B8: O1 customer, 30 days post first order | C8: O1 | D8: O1->O2 | E8: CRM | F8: last category | G8: none | H8: Not yet repeated | I8: Second-order accelerator | J8: Rs200 off next order (30d, min Rs1,499) | K8: Rs1,499 | L8: 'Here's Rs200 to complete your kit' | M8: Email/SMS | N8: 30d after O1 | O8: Places O2 | P8: Med | Q8: High
A9: 6 | B9: High-intent non-purchaser (ATC abandon) | C9: New/Repeat | D9: - | E9: Any | F9: in-cart SKU | G9: abandoned | H9: Left at cart | I9: Cart-abandon flow (3 steps) | J9: Reminder; light incentive step 3 | K9: - | L9: 'Still thinking? Your cart's waiting' | M9: Email/SMS/Push | N9: ATC no purchase | O9: Returns & buys | P9: Low | Q9: High
A10: 7 | B10: Payment-failed / COD-abandon | C10: New | D10: - | E10: Any | F10: in-cart SKU | G10: abandoned at pay | H10: Payment dropped | I10: Instant UPI-retry link + prepaid perks | J10: Waive COD fee + free ship on prepaid | K10: - | L10: 'Complete via UPI - save Rs79 + free shipping' | M10: SMS/WhatsApp | N10: add_payment_info no purchase | O10: Retries, completes | P10: Low | Q10: High
A11: 8 | B11: Watch-band single buyer | C11: New/Repeat | D11: any | E11: Any | F11: Watch bands | G11: 1 band | H11: Single-band | I11: Multi-band escalator | J11: Buy 2 -15%, 3 -20% | K11: - | L11: 'Build your band wardrobe' | M11: On-site PDP | N11: Band PDP | O11: Adds 2nd/3rd band | P11: Low | Q11: Med
A12: 9 | B12: Backpack browser, high hesitation | C12: New | D12: O1 | E12: Paid/Organic | F12: Backpacks | G12: viewed 2+ | H12: Not converting (0.77%) | I12: Risk reversal + carry-system bundle | J12: Kit -12% + easy returns | K12: - | L12: '30-day easy returns + complete your carry' | M12: On-site PDP | N12: Repeat bag views | O12: Converts / bundles | P12: Med | Q12: Med
A13: 10 | B13: Gift shopper (festive/wedding) | C13: New | D13: O1 | E13: Organic/Direct | F13: Gifting | G13: browsing gifts | H13: Gifting intent | I13: Gift finder + curated bundles + paid wrap | J13: Curated bundle + gift wrap add-on | K13: - | L13: 'Perfect gifts, sorted by budget' | M13: On-site + CRM | N13: Gifting nav / season | O13: Buys curated gift | P13: Low | Q13: High
A14: 11 | B14: High-AOV / VIP repeat | C14: Repeat | D14: O3+ | E14: Direct/Email | F14: Premium (power/bags) | G14: high | H14: Most valuable | I14: VIP early access + membership + concierge | J14: Early access; DO Club | K14: - | L14: 'VIP early access to new drops' | M14: Email/SMS | N14: Top-decile spend | O14: Buys premium, joins club | P14: Low | Q14: Med
A15: 12 | B15: Desktop considered shopper | C15: New/Repeat | D15: any | E15: Any | F15: Desk/bags | G15: larger basket | H15: Higher AOV device | I15: Bundle-heavy merch + shop-the-look | J15: Setup/kit bundles | K15: - | L15: 'Shop the full setup' | M15: On-site desktop | N15: Desktop session | O15: Builds bigger basket | P15: Low | Q15: Med
... A17: 14 | B17: Single-category repeat (cases only) | C17: Repeat | D17: O2/O3+ | E17: CRM | F17: cases only | G17: - | H17: Mono-category | I17: Category-penetration intro | J17: First-in-new-category incentive | K17: - | L17: 'Discover your next essential' | M17: Email/SMS | N17: 2+ orders, 1 category | O17: Buys adjacent category | P17: Med | Q17: Med

Sheet 9. Revenue Leakages
A1: REVENUE LEAKAGES
A2: Where money is leaking today, ranked. Metrics OBSERVED from GA4 funnel/device/channel; benchmarks INFERRED.
A3: ID | B3: Area | C3: Funnel Stage | D3: Issue | E3: Evidence (OBS/INF) | F3: Current Metric | G3: Benchmark | H3: Estimated Gap | I3: Revenue Impact | J3: Root-Cause Hypothesis | K3: Tactical Fix | L3: Effort | M3: Time to Fix | N3: Confidence | O3: Priority
A4: LK01 | B4: Mobile conversion | C4: Full funnel | D4: Mobile CVR ~half of desktop on 91% of traffic | E4: OBS: mobile 0.95% vs desktop 1.96% CVR; mobile=49.1M sessions | F4: 0.95% | G4: 1.4-2.0% | H4: ~0.5-1.0pp on 49M sessions | I4: Very High | J4: Mobile PDP/checkout friction, slow LCP, payment UX | K4: Mobile checkout+PDP sprint; express/UPI checkout (ID11/ID12) | L4: High | M4: <30d | N4: High | O4: High
A5: LK02 | B5: Payment | C5: Payment | D5: 42% drop after entering payment info | E5: OBS: add_payment_info 1.07M -> purchase 623k | F5: 58% pay->purchase | G5: 75-85% | H5: ~0.2-0.4M lost orders | I5: Very High | J5: Payment failures, limited methods, no retry | K5: New PSP stack + UPI + retry + SMS recovery (ID12/ID47) | L5: Med | M5: <14d | N5: High | O5: High
A6: LK03 | B6: Cart -> checkout | C6: Cart | D6: Only 26% of ATC begin checkout | E6: OBS: ATC 5.99M -> begin_checkout 1.55M | F6: 25.8% | G6: 35-45% | H6: large | I6: High | J6: No cart progress/urgency, unclear shipping/offers, friction | K6: Cart drawer + progress bar + FBT + free-ship clarity (ID50/ID06) | L6: Med | M6: <14d | N6: Med | O6: High
A7: LK04 | B7: CRM / owned channels | C7: Retention | D7: Email+SMS+Push = ~0.55% of revenue | E7: OBS: Email Rs5.7M + SMS Rs0.75M + Push Rs0.88M vs Rs1.34B total | F7: 0.55% rev | G7: 8-15% rev | H7: ~Rs50-150M | I7: Very High | J7: Flows not built; tiny opt-in base; SMS underused despite 4.2% CVR | K7: Build lifecycle flows; scale SMS/WhatsApp (ID19-24) | L7: Med | M7: <14d | N7: High | O7: High
A8: LK05 | B8: Paid Social efficiency | C8: Acquisition | D8: 29M sessions at 0.38% CVR, RPV Rs9.3 | E8: OBS: Paid Social biggest channel, lowest RPV | F8: 0.38% CVR | G8: 0.6-1.0% | H8: huge (volume) | I8: High | J8: Message-LP mismatch, homepage routing, cold traffic | K8: Matched LPs + first-order hook + quiz (ID29) | L8: Med | M8: <14d | N8: Med | O8: High
A9: LK06 | B9: AOV / attach | C9: Cart/PDP | D9: Phone-case ASP ~Rs1,068 on 57% of views; low attach | E9: OBS: cases 31M views, ASP Rs1,068, view->purchase 1.2% | F9: ~Rs1,068 ASP | G9: +15-30% w/ attach | H9: Med-High | I9: No systematic attach/FBT on hero category | J9: Case attach engine + FBT + tier upsell (ID01/ID13/ID16) | K9: Low | L9: <7d | M9: High | N9: High
A10: LK07 | B10: Backpack conversion | C10: PDP | D10: Bags convert far below other big cats | E10: OBS: backpacks view->purchase 0.77%, ATC 3.7% | F10: 0.77% | G10: 1.2-1.6% | H10: Med | I10: High-consideration hesitation, weak risk reversal | J10: Risk reversal + carry bundle (ID39/ID03) | K10: Low | L10: <7d | M10: Med | N10: Med
A11: LK08 | B11: Product discovery / PLP | C11: Discovery | D11: /collection PLP converts at 0.33% | E11: OBS: /collection 3.3M sessions, 0.33% CVR vs homepage 1.54% | F11: 0.33% | G11: 0.8-1.2% | H11: Med | I11: Weak sort, no price-point/use-case entry, choice overload | J11: Bestseller sort + price-point stores + device hub (ID25/26/27) | K11: Low | L11: <7d | M11: Med | N11: High
A12: LK09 | B12: Gifting | C12: Discovery | D12: Gifting ~Rs3.2M despite infra | E12: OBS: 16xx cats Rs3.2M; gift cards + corporate gifting exist | F12: ~Rs3.2M | G12: much higher | H12: Med (seasonal) | I12: No gift finder/hub activation | J12: Gift hub + finder + corporate lead-gen (ID09/ID56) | K12: Med | L12: <14d | M12: Med | N12: Med
A13: LK10 | B13: Search | C13: Discovery | D13: Zero-result & weak search recovery | E13: OBS: internal analytics tracks zero-results & search CVR | F13: tracked | G13: lower zero-result | H13: Med | I13: No synonyms/typo tolerance/empty-state recs | J13: Search config + zero-result recovery (ID38) | K13: Med | L13: <14d | M13: Med | N13: Med
A14: LK11 | B14: New-user trust | C14: Consideration | D14: New CVR 0.69% (66% of traffic) | E14: OBS: new 0.69% vs returning 1.77% | F14: 0.69% | G14: 1.0-1.3% | H14: High | I14: Weak trust cues/ETA/social proof for new visitors | J14: PDP trust pack + reviews/UGC (ID14/ID51) | K14: Med | L14: <14d | M14: Med | N14: High
A15: LK12 | B15: Repeat / O1->O2 | C15: Retention | D15: O1->O2 not accelerated | E15: OBS: returning drive 57% of revenue, convert 2.56x | F15: - | G15: +repeat rate | H15: High | I15: No second-order trigger/loyalty visibility | J15: O1->O2 accelerator + loyalty surfacing (ID18/ID30) | K15: Low | L15: <7d | M15: Med | N15: High
A16: LK13 | B16: Shipping/COD friction | C16: Checkout | D16: Inconsistent free-ship + Rs79-99 COD fee | E16: INF: reported Rs749 vs Rs1,199 free-ship; COD fee varies | F16: unclear | G16: clear prepaid nudge | H16: Med | I16: Confusing thresholds; COD RTO cost | J16: Prepaid free-ship reframing (ID07/ID53) | K16: Low | L16: <7d | M16: Med | N16: High
A17: LK14 | B17: Post-purchase | C17: Post-purchase | D17: No thank-you upsell / order bump | E17: INF: standard gap | F17: - | G17: +2-5% AOV | H17: Low-Med | I17: No one-click upsell/order-bump live | J17: Thank-you upsell + order bump (ID17/ID42) | K17: Low | L17: <14d | M17: Med | N17: Med

Sheet 10. Experiment Backlog
A1: EXPERIMENT BACKLOG
A2: Living experimentation tracker. Seeded from the top 24 ideas by priority. Fill Owner/Dates/Result as you run them.
A3: Exp ID | B3: Priority | C3: Hypothesis | D3: Initiative | E3: Segment | F3: Category | G3: SKUs | H3: Control | I3: Variant | J3: Offer | K3: Placement | L3: Primary Metric | M3: Secondary Metric | N3: Guardrail Metric | O3: Expected Uplift | P3: Effort | Q3: Test Duration | R3: Sample Req. | S3: Owner | T3: Start Date | U3: End Date | V3: Status | W3: Result | X3: Decision | Y3: Next Step
A4: EXP01 | B4: 51.2 | C4: If we phone case attach engine (screen guard + charm + strap), then units per transaction improves for all case buyers because The case is the wedge; a discounted, compatible attach is the single most proven... | D4: Phone Case Attach Engine (screen guard + charm + strap) | E4: New & Repeat | F4: Phone Cases | G4: 1101,1103,1815,1812 | H4: Current experience | I4: New mechanic | J4: 30-50% off attach items with a case | K4: PDP below CTA + Cart FBT rail | L4: Units per Transaction | M4: AOV | N4: Case CVR, return rate | O4: +8-15% | P4: Easy | Q4: 2-4 wks | R4: per power calc | S4: Unassigned | V4: Backlog
A5: EXP02 | B5: 51.2 | C5: If we cart & checkout abandonment flow (email+sms+push), then revenue from crm audiences improves for abandoners because Recovering even a small % of the 1.5M checkout-abandoners is large; owned channe... | D5: Cart & checkout abandonment flow (email+SMS+push) | E5: High-intent non-purchasers | F5: Cross-category | G5: all | H5: Current experience | I5: New mechanic | J5: Reminder; light incentive on step 3 | K5: Email/SMS/Push | L5: Revenue from CRM audiences | M5: Checkout Completion | N5: Unsub rate, discount leakage | O5: + | P5: Easy | Q5: 2-4 wks | R5: per power calc | S5: Unassigned | V5: Backlog
A6: EXP03 | B6: 48 | C6: If we cart low-price add-on rail (impulse skus), then units per transaction improves for all carts because Frictionless one-tap add of a cheap complement is pure incremental margin with z... | D6: Cart low-price add-on rail (impulse SKUs) | E6: New & Repeat | F6: Impulse tech | G6: 1811,1812,1815,1705 | H6: Current experience | I6: New mechanic | J6: No discount - convenience placement | K6: Cart add-on rail | L6: Units per Transaction | M6: AOV | N6: Cart abandonment | O6: +3-6% | P6: Very Easy | Q6: 2-4 wks | R6: per power calc | S6: Unassigned | V6: Backlog
A7: EXP04 | B7: 48 | C7: If we bestseller & high-margin sku prioritisation on plp/home, then conversion rate improves for all browsers because Leading with proven winners raises blended CVR and margin without new traffic.... | D7: Bestseller & high-margin SKU prioritisation on PLP/home | E7: New & Repeat | F7: Cross-category | G7: bestsellers | H7: Current experience | I7: New mechanic | J7: None | K7: PLP sort + homepage | L7: Conversion Rate | M7: Revenue per Visitor | N7: Long-tail exposure | O7: + | P7: Very Easy | Q7: 2-4 wks | R7: per power calc | S7: Unassigned | V7: Backlog
A8: EXP05 | B8: 41 | C8: If we prepaid free-shipping + rs79 cod-fee reframing, then checkout completion improves for cod-inclined shoppers because Shifting COD->prepaid cuts RTO cost and lifts contribution margin more than the ... | D8: Prepaid free-shipping + Rs79 COD-fee reframing | E8: New | F8: Cross-category | G8: all | H8: Current experience | I8: New mechanic | J8: Free ship + waive COD fee on prepaid | K8: Cart + Checkout | L8: Checkout Completion | M8: Contribution margin | N8: Overall CVR | O8: + | P8: Easy | Q8: 2-4 wks | R8: per power calc | S8: Unassigned | V8: Backlog
A9: EXP06 | B9: 32.8 | C9: If we power bank + magsafe case cross-sell bundle, then cross-category purchase improves for power-bank & magsafe shoppers because Qi2/MagSafe interoperability is a real functional reason to pair; premium buyers... | D9: Power Bank + MagSafe Case cross-sell bundle | E9: New & Repeat | F9: Power Banks | G9: 1809,1103 | H9: Current experience | I9: New mechanic | J9: Bundle -10% vs buying separately | K9: PDP FBT + Cart | L9: Cross-category Purchase | M9: AOV | N9: Power bank CVR | O9: +10-18% | P9: Easy | Q9: 2-4 wks | R9: per power calc | S9: Unassigned | V9: Backlog
A10: EXP07 | B10: 32.8 | C10: If we watch-band multi-pack ('band wardrobe'), then units per transaction improves for watch-band shoppers because Bands are a wardrobe item (match outfit/occasion); multi-buy escalators convert ... | D10: Watch-band multi-pack ('Band Wardrobe') | E10: New & Repeat | F10: Apple Watch Bands | G10: 1801 | H10: Current experience | I10: New mechanic | J10: Buy 2 -15%, 3+ -20% | K10: PDP selector + PLP banner | L10: Units per Transaction | M10: AOV | N10: Band margin | O10: +12-20% | P10: Easy | Q10: 2-4 wks | R10: per power calc | S10: Unassigned | V10: Backlog
A11: EXP08 | B11: 30.7 | C11: If we reviews & ugc amplification on high-traffic pdps, then conversion rate improves for pdp visitors because Photo reviews + compatibility Q&A directly reduce the doubts that stall accessor... | D11: Reviews & UGC amplification on high-traffic PDPs | E11: New | F11: Cross-category | G11: top PDPs | H11: Current experience | I11: New mechanic | J11: None | K11: PDP | L11: Conversion Rate | M11: New User Conversion | N11: Review authenticity | O11: + | P11: Easy | Q11: 2-4 wks | R11: per power calc | S11: Unassigned | V11: Backlog
A12: EXP09 | B12: 30.7 | C12: If we prepaid-only deeper offer to convert cod share, then contribution margin improves for cod-preferring because Shifting COD->prepaid saves RTO/logistics cost that exceeds the incentive - net ... | D12: Prepaid-only deeper offer to convert COD share | E12: New | F12: Cross-category | G12: all | H12: Current experience | I12: New mechanic | J12: Prepaid-only extra 5% / gift | K12: Checkout | L12: Contribution margin | M12: Checkout Completion | N12: Overall CVR | O12: Neutral | P12: Easy | Q12: 2-4 wks | R12: per power calc | S12: Unassigned | V12: Backlog
A13: EXP10 | B13: 28.8 | C13: If we express/1-tap payment (upi intent, wallets, tokenised cards), then checkout completion improves for all checkout because A large share of the payment-stage drop is failed/abandoned payment, directly re... | D13: Express/1-tap payment (UPI intent, wallets, tokenised cards) | E13: New & Repeat | F13: Cross-category | G13: all | H13: Current experience | I13: New mechanic | J13: None | K13: Payment page | L13: Checkout Completion | M13: Revenue per Visitor | N13: Fraud, chargebacks | O13: ++ | P13: Moderate | Q13: 2-4 wks | R13: per power calc | S13: Unassigned | V13: Backlog
A14: EXP11 | B14: 24.6 | C14: If we second-order accelerator coupon on thank-you + email, then repeat purchase improves for first-order buyers because The O1->O2 jump is the highest-leverage retention moment; a bounded incentive pu... | D14: Second-order accelerator coupon on thank-you + email | E14: O1 | F14: Cross-category | G14: all | H14: Current experience | I14: New mechanic | J14: Rs200 off next order in 30 days (min Rs1,499) | K14: Thank-you + email/SMS | L14: Repeat Purchase | M14: O1->O2 rate | N14: Margin, redemption cannibalisation | O14: Neutral | P14: Easy | Q14: 2-4 wks | R14: per power calc | S14: Unassigned | V14: Backlog
A15: EXP12 | B15: 24.6 | C15: If we first-order offer clarity + email/phone capture popup, then new user conversion improves for new visitors because First-order clarity + capture both lifts new CVR and builds the owned audience t... | D15: First-order offer clarity + email/phone capture popup | E15: New | F15: Cross-category | G15: all | H15: Current experience | I15: New mechanic | J15: WELCOME300 (Rs300 off > Rs2,299) | K15: Popup + sticky bar + LP | L15: New User Conversion | M15: Revenue from CRM audiences | N15: Discount on would-buy-anyway | O15: + | P15: Easy | Q15: 2-4 wks | R15: per power calc | S15: Unassigned | V15: Backlog
... A27: EXP24 | B27: 23 | C27: If we abandonment + prepaid-fail sms with upi retry link, then checkout completion improves for payment-fail/cod abandon because Instant, one-tap retry on the highest-CVR channel recovers already-decided buyer... | D27: Abandonment + prepaid-fail SMS with UPI retry link | E27: High-intent non-purchasers | F27: Cross-category | G27: all | H27: Current experience | I27: New mechanic | J27: UPI retry + COD-fee saving | K27: SMS/WhatsApp | L27: Checkout Completion | M27: Contribution margin | N27: Message compliance | O27: ++ | P27: Moderate | Q27: 2-4 wks | R27: per power calc | S27: Unassigned | V27: Backlog

Sheet 11. Financial Model
A1: FINANCIAL MODEL (base case)
A2: Yellow = editable assumptions. All outputs are formulas - change any assumption and the model recomputes. Uplifts are HYPOTHESES; ground them with test reads. Traffic/baselines from GA4 'DO - GA4' (273672074), via Windsor.ai, pulled 2026-08-10
A4: GLOBAL ASSUMPTIONS
A5: Blended gross margin % | B5: 0.55
A6: Payment cost % of revenue | B6: 0.02
A7: Incremental shipping cost / order (Rs) | B7: 40
A8: Best-case multiplier (on contribution) | B8: 1.5
A9: Worst-case multiplier (on contribution) | B9: 0.4
A11: Initiative | B11: Eligible Traffic | C11: Base CVR | D11: Exp. CVR | E11: CVR Uplift | F11: Base Orders | G11: Exp. Orders | H11: Incr. Orders | I11: Base AOV | J11: Exp. AOV | K11: AOV Uplift | L11: Incr. Revenue | M11: Disc % | N11: Discount Cost | O11: Gift COGS/ord | P11: Gift COGS | Q11: Incr. Shipping | R11: Payment Cost | S11: Incr. COGS | T11: Incr. Gross Margin | U11: Program Spend | V11: Incr. Contribution | W11: Rev ROI | X11: Contrib ROI | Y11: Best Case | Z11: Worst Case
A12: ID11 Mobile checkout & PDP sprint | B12: 49120510 | C12: 0.0095 | D12: 0.0109 | E12: =IF(C12=0,"n/a",D12/C12-1) | F12: =B12*C12 | G12: =B12*D12 | H12: =G12-F12 | I12: 2362 | J12: 2362 | K12: =IF(I12=0,"n/a",J12/I12-1) | L12: =G12*J12-F12*I12 | M12: 0 | N12: =M12*L12 | O12: 0 | P12: =O12*H12 | Q12: =H12*$B$7 | R12: =L12*$B$6 | S12: =L12*(1-$B$5) | T12: =L12-S12 | U12: =N12+P12 | V12: =T12-N12-P12-Q12-R12 | W12: =IF(U12=0,"no spend",L12/U12) | X12: =IF(U12=0,"no spend",V12/U12) | Y12: =V12*$B$8 | Z12: =V12*$B$9
A13: ID12 Express/UPI payment + retry | B13: 53984509 | C13: 0.01025 | D13: 0.0112 | E13: =IF(C13=0,"n/a",D13/C13-1) | F13: =B13*C13 | G13: =B13*D13 | H13: =G13-F13 | I13: 2429 | J13: 2429 | K13: =IF(I13=0,"n/a",J13/I13-1) | L13: =G13*J13-F13*I13 | M13: 0 | N13: =M13*L13 | O13: 0 | P13: =O13*H13 | Q13: =H13*$B$7 | R13: =L13*$B$6 | S13: =L13*(1-$B$5) | T13: =L13-S13 | U13: =N13+P13 | V13: =T13-N13-P13-Q13-R13 | W13: =IF(U13=0,"no spend",L13/U13) | X13: =IF(U13=0,"no spend",V13/U13) | Y13: =V13*$B$8 | Z13: =V13*$B$9
A14: ID19 Cart/checkout abandonment flow | B14: 5360000 | C14: 0 | D14: 0.03 | E14: =IF(C14=0,"n/a",D14/C14-1) | F14: =B14*C14 | G14: =B14*D14 | H14: =G14-F14 | I14: 2429 | J14: 2429 | K14: =IF(I14=0,"n/a",J14/I14-1) | L14: =G14*J14-F14*I14 | M14: 0.05 | N14: =M14*L14 | O14: 0 | P14: =O14*H14 | Q14: =H14*$B$7 | R14: =L14*$B$6 | S14: =L14*(1-$B$5) | T14: =L14-S14 | U14: =N14+P14 | V14: =T14-N14-P14-Q14-R14 | W14: =IF(U14=0,"no spend",L14/U14) | X14: =IF(U14=0,"no spend",V14/U14) | Y14: =V14*$B$8 | Z14: =V14*$B$9
A15: ID47 Payment-fail SMS/UPI retry | B15: 446000 | C15: 0 | D15: 0.12 | E15: =IF(C15=0,"n/a",D15/C15-1) | F15: =B15*C15 | G15: =B15*D15 | H15: =G15-F15 | I15: 2429 | J15: 2429 | K15: =IF(I15=0,"n/a",J15/I15-1) | L15: =G15*J15-F15*I15 | M15: 0 | N15: =M15*L15 | O15: 0 | P15: =O15*H15 | Q15: =H15*$B$7 | R15: =L15*$B$6 | S15: =L15*(1-$B$5) | T15: =L15-S15 | U15: =N15+P15 | V15: =T15-N15-P15-Q15-R15 | W15: =IF(U15=0,"no spend",L15/U15) | X15: =IF(U15=0,"no spend",V15/U15) | Y15: =V15*$B$8 | Z15: =V15*$B$9
A16: ID01 Phone-case attach engine | B16: 387008 | C16: 1 | D16: 1 | E16: =IF(C16=0,"n/a",D16/C16-1) | F16: =B16*C16 | G16: =B16*D16 | H16: =G16-F16 | I16: 1068 | J16: 1175 | K16: =IF(I16=0,"n/a",J16/I16-1) | L16: =G16*J16-F16*I16 | M16: 0 | N16: =M16*L16 | O16: 0 | P16: =O16*H16 | Q16: =H16*$B$7 | R16: =L16*$B$6 | S16: =L16*(1-$B$5) | T16: =L16-S16 | U16: =N16+P16 | V16: =T16-N16-P16-Q16-R16 | W16: =IF(U16=0,"no spend",L16/U16) | X16: =IF(U16=0,"no spend",V16/U16) | Y16: =V16*$B$8 | Z16: =V16*$B$9
A17: ID02 Power bank + MagSafe case bundle | B17: 127803 | C17: 1 | D17: 1 | E17: =IF(C17=0,"n/a",D17/C17-1) | F17: =B17*C17 | G17: =B17*D17 | H17: =G17-F17 | I17: 3108 | J17: 3357 | K17: =IF(I17=0,"n/a",J17/I17-1) | L17: =G17*J17-F17*I17 | M17: 0.03 | N17: =M17*L17 | O17: 0 | P17: =O17*H17 | Q17: =H17*$B$7 | R17: =L17*$B$6 | S17: =L17*(1-$B$5) | T17: =L17-S17 | U17: =N17+P17 | V17: =T17-N17-P17-Q17-R17 | W17: =IF(U17=0,"no spend",L17/U17) | X17: =IF(U17=0,"no spend",V17/U17) | Y17: =V17*$B$8 | Z17: =V17*$B$9
A18: ID03 Bag carry-system bundle | B18: 107901 | C18: 1 | D18: 1 | E18: =IF(C18=0,"n/a",D18/C18-1) | F18: =B18*C18 | G18: =B18*D18 | H18: =G18-F18 | I18: 2000 | J18: 2300 | K18: =IF(I18=0,"n/a",J18/I18-1) | L18: =G18*J18-F18*I18 | M18: 0.05 | N18: =M18*L18 | O18: 0 | P18: =O18*H18 | Q18: =H18*$B$7 | R18: =L18*$B$6 | S18: =L18*(1-$B$5) | T18: =L18-S18 | U18: =N18+P18 | V18: =T18-N18-P18-Q18-R18 | W18: =IF(U18=0,"no spend",L18/U18) | X18: =IF(U18=0,"no spend",V18/U18) | Y18: =V18*$B$8 | Z18: =V18*$B$9
A19: ID04 Watch-band multi-pack | B19: 107273 | C19: 1 | D19: 1 | E19: =IF(C19=0,"n/a",D19/C19-1) | F19: =B19*C19 | G19: =B19*D19 | H19: =G19-F19 | I19: 1108 | J19: 1241 | K19: =IF(I19=0,"n/a",J19/I19-1) | L19: =G19*J19-F19*I19 | M19: 0.08 | N19: =M19*L19 | O19: 0 | P19: =O19*H19 | Q19: =H19*$B$7 | R19: =L19*$B$6 | S19: =L19*(1-$B$5) | T19: =L19-S19 | U19: =N19+P19 | V19: =T19-N19-P19-Q19-R19 | W19: =IF(U19=0,"no spend",L19/U19) | X19: =IF(U19=0,"no spend",V19/U19) | Y19: =V19*$B$8 | Z19: =V19*$B$9
A20: ID06 Cart free-gift ladder | B20: 553257 | C20: 1 | D20: 1 | E20: =IF(C20=0,"n/a",D20/C20-1) | F20: =B20*C20 | G20: =B20*D20 | H20: =G20-F20 | I20: 2429 | J20: 2599 | K20: =IF(I20=0,"n/a",J20/I20-1) | L20: =G20*J20-F20*I20 | M20: 0 | N20: =M20*L20 | O20: 45 | P20: =O20*H20 | Q20: =H20*$B$7 | R20: =L20*$B$6 | S20: =L20*(1-$B$5) | T20: =L20-S20 | U20: =N20+P20 | V20: =T20-N20-P20-Q20-R20 | W20: =IF(U20=0,"no spend",L20/U20) | X20: =IF(U20=0,"no spend",V20/U20) | Y20: =V20*$B$8 | Z20: =V20*$B$9
A21: ID13 PDP Frequently-Bought-Together | B21: 553257 | C21: 1 | D21: 1 | E21: =IF(C21=0,"n/a",D21/C21-1) | F21: =B21*C21 | G21: =B21*D21 | H21: =G21-F21 | I21: 2429 | J21: 2550 | K21: =IF(I21=0,"n/a",J21/I21-1) | L21: =G21*J21-F21*I21 | M21: 0 | N21: =M21*L21 | O21: 0 | P21: =O21*H21 | Q21: =H21*$B$7 | R21: =L21*$B$6 | S21: =L21*(1-$B$5) | T21: =L21-S21 | U21: =N21+P21 | V21: =T21-N21-P21-Q21-R21 | W21: =IF(U21=0,"no spend",L21/U21) | X21: =IF(U21=0,"no spend",V21/U21) | Y21: =V21*$B$8 | Z21: =V21*$B$9
A22: ID18 O1->O2 accelerator | B22: 250000 | C22: 0.3 | D22: 0.36 | E22: =IF(C22=0,"n/a",D22/C22-1) | F22: =B22*C22 | G22: =B22*D22 | H22: =G22-F22 | I22: 2429 | J22: 2429 | K22: =IF(I22=0,"n/a",J22/I22-1) | L22: =G22*J22-F22*I22 | M22: 0.082 | N22: =M22*L22 | O22: 0 | P22: =O22*H22 | Q22: =H22*$B$7 | R22: =L22*$B$6 | S22: =L22*(1-$B$5) | T22: =L22-S22 | U22: =N22+P22 | V22: =T22-N22-P22-Q22-R22 | W22: =IF(U22=0,"no spend",L22/U22) | X22: =IF(U22=0,"no spend",V22/U22) | Y22: =V22*$B$8 | Z22: =V22*$B$9
A23: ID29 Paid-Social matched LPs | B23: 29240422 | C23: 0.0038 | D23: 0.0045 | E23: =IF(C23=0,"n/a",D23/C23-1) | F23: =B23*C23 | G23: =B23*D23 | H23: =G23-F23 | I23: 2429 | J23: 2429 | K23: =IF(I23=0,"n/a",J23/I23-1) | L23: =G23*J23-F23*I23 | M23: 0.05 | N23: =M23*L23 | O23: 0 | P23: =O23*H23 | Q23: =H23*$B$7 | R23: =L23*$B$6 | S23: =L23*(1-$B$5) | T23: =L23-S23 | U23: =N23+P23 | V23: =T23-N23-P23-Q23-R23 | W23: =IF(U23=0,"no spend",L23/U23) | X23: =IF(U23=0,"no spend",V23/U23) | Y23: =V23*$B$8 | Z23: =V23*$B$9
... A29: ID33 Device-launch attach | B29: 2000000 | C29: 0.012 | D29: 0.014 | E29: =IF(C29=0,"n/a",D29/C29-1) | F29: =B29*C29 | G29: =B29*D29 | H29: =G29-F29 | I29: 1200 | J29: 1500 | K29: =IF(I29=0,"n/a",J29/I29-1) | L29: =G29*J29-F29*I29 | M29: 0 | N29: =M29*L29 | O29: 0 | P29: =O29*H29 | Q29: =H29*$B$7 | R29: =L29*$B$6 | S29: =L29*(1-$B$5) | T29: =L29-S29 | U29: =N29+P29 | V29: =T29-N29-P29-Q29-R29 | W29: =IF(U29=0,"no spend",L29/U29) | X29: =IF(U29=0,"no spend",V29/U29) | Y29: =V29*$B$8 | Z29: =V29*$B$9
A30: TOTAL (base case) | H30: =SUM(H12:H29) | L30: =SUM(L12:L29) | N30: =SUM(N12:N29) | P30: =SUM(P12:P29) | Q30: =SUM(Q12:Q29) | R30: =SUM(R12:R29) | S30: =SUM(S12:S29) | T30: =SUM(T12:T29) | U30: =SUM(U12:U29) | V30: =SUM(V12:V29) | Y30: =SUM(Y12:Y29) | Z30: =SUM(Z12:Z29)
A32: Note: Incr. Gross Margin (col T) = Incr. Revenue - Incr. COGS; Incr. Contribution (col V) = Gross Margin - Discount - Gift - Shipping - Payment. Program Spend (col U) = promotional cost (discount + gift) used for ROI. Uplift %s are base-case HYPOTHESES - replace with test reads.

Sheet 12. 30-Day Action Plan
A1: 30-DAY ACTION PLAN
A2: Execution roadmap. Week 1 = fastest, highest-priority, no/low discount. Sequenced by Time-to-Launch and Priority.
A3: Week | B3: Priority | C3: Initiative | D3: Category | E3: Owner | F3: Action | G3: Dependency | H3: Start Date | I3: Launch Date | J3: Metric | K3: Expected Impact | L3: Status
A4: Week 1 | B4: 51.2 | C4: Phone Case Attach Engine (screen guard + charm + strap) | D4: Phone Cases | E4: Unassigned | F4: On every phone-case PDP + cart, show a 'Complete your case' rail: matching tempered-glass ... | G4: Merch rule / FBT widget | J4: Units per Transaction | K4: High | L4: Not started
A5: Week 1 | B5: 51.2 | C5: Cart & checkout abandonment flow (email+SMS+push) | D5: Cross-category | E5: Unassigned | F5: 3-step abandonment series: 30min reminder, 24h with social proof, 48h with a modest incent... | G5: CRM/ESP flows + events | J5: Revenue from CRM audiences | K5: High | L5: Not started
A6: Week 1 | B6: 48 | C6: Cart low-price add-on rail (impulse SKUs) | D6: Impulse tech | E6: Unassigned | F6: In cart, show a horizontal 'Add for a little more' rail of high-margin impulse SKUs <Rs499... | G6: Cart widget | J6: Units per Transaction | K6: Med | L6: Not started
A7: Week 1 | B7: 48 | C7: Bestseller & high-margin SKU prioritisation on PLP/home | D7: Cross-category | E7: Unassigned | F7: Re-sort PLPs and homepage rails to lead with proven high-CVR, high-margin bestsellers (Wra... | G7: Merch sort rules | J7: Conversion Rate | K7: Med | L7: Not started
A8: Week 1 | B8: 41 | C8: Prepaid free-shipping + Rs79 COD-fee reframing | D8: Cross-category | E8: Unassigned | F8: Make free shipping explicit and prepaid-gated with a visible bar ('You're Rs X from free s... | G8: Checkout config | J8: Checkout Completion | K8: High | L8: Not started
A9: Week 1 | B9: 32.8 | C9: Power Bank + MagSafe Case cross-sell bundle | D9: Power Banks | E9: Unassigned | F9: On Loop Qi2 power-bank PDPs, add 'Powers up perfectly with' a MagSafe case at bundle price... | G9: FBT widget | J9: Cross-category Purchase | K9: High | L9: Not started
A10: Week 1 | B10: 32.8 | C10: Watch-band multi-pack ('Band Wardrobe') | D10: Apple Watch Bands | E10: Unassigned | F10: On Apple Watch band PDPs offer buy-2-save-15% / buy-3-save-20% across bands (mix leather/s... | G10: Qty-tier promo | J10: Units per Transaction | K10: Med-High | L10: Not started
A11: Week 1 | B11: 30.7 | C11: Reviews & UGC amplification on high-traffic PDPs | D11: Cross-category | E11: Unassigned | F11: Surface photo reviews, review count and Q&A prominently on top PDPs; seed Q&A for compatib... | G11: Reviews widget | J11: Conversion Rate | K11: Med | L11: Not started
A12: Week 2 | B12: 30.7 | C12: Prepaid-only deeper offer to convert COD share | D12: Cross-category | E12: Unassigned | F12: Offer the best price/gift ONLY on prepaid (COD gets base price); reframe as 'prepaid perks... | G12: Checkout rules | J12: Contribution margin | K12: Med | L12: Not started
A13: Week 2 | B13: 28.8 | C13: Express/1-tap payment (UPI intent, wallets, tokenised cards) | D13: Cross-category | E13: Unassigned | F13: Add UPI-intent one-tap, popular wallets, saved/tokenised cards and a prominent 'Pay by UPI... | G13: PSP integration + retry flow | J13: Checkout Completion | K13: Very High | L13: Not started
A14: Week 2 | B14: 24.6 | C14: Second-order accelerator coupon on thank-you + email | D14: Cross-category | E14: Unassigned | F14: Give every first-time buyer a time-boxed next-order incentive (e.g. Rs200 off next order w... | G14: Coupon + CRM flow | J14: Repeat Purchase | K14: High | L14: Not started
A15: Week 2 | B15: 24.6 | C15: First-order offer clarity + email/phone capture popup | D15: Cross-category | E15: Unassigned | F15: Tighten the welcome popup: 'Get Rs300 off your first order over Rs2,299 - unlock now' with... | G15: Popup + CRM | J15: New User Conversion | K15: Med-High | L15: Not started
... A33: Week 3 | B33: 18.4 | C33: Cart free-gift ladder tied to AOV bands | D33: Cross-category | E33: Unassigned | F33: Cart progress bar with a 2-rung gift ladder: spend Rs1,999 -> free premium cable bind; spe... | G33: Cart GWP engine | J33: AOV | K33: High | L33: Not started

Sheet 13. Research Sources
A1: RESEARCH SOURCES
A2: Auditable source log. Internal data = High reliability; external brand tactics = 'Reported' (search-index, re-verify live).
A3: Source ID | B3: Brand / Entity | C3: Source Type | D3: Title / Description | E3: URL | F3: Date | G3: What It Supports | H3: Reliability | I3: Used In
A4: S01 | B4: DailyObjects | C4: Internal analytics | D4: GA4 property 'DO - GA4' (273672074) via Windsor.ai - funnel, device, channel, new/return, category, landing pages | E4: GA4 'DO - GA4' (273672074), via Windsor.ai, pulled 2026-08-10 | F4: 2026-08-10 | G4: All internal metrics & category economics | H4: High | I4: All GA4-cited ideas
A5: S02 | B5: DailyObjects | C5: Internal file | D5: Order-level file daily-marketing-report-v2-2.csv (Order Total, Qty, Discount, Payment, Source) | E5: Google Drive (internal) | F5: 2025-10 | G5: AOV/threshold/discount/payment analysis | H5: High | I5: ID06-08,49,53; Tab 7
A6: S03 | B6: DailyObjects | C6: Internal deck | D6: VoC deck - 80,303 reviews across 11,771 SKUs + returns | E6: Google Drive (internal) | F6: 2026-08 | G6: Social proof, returns, PDP trust | H6: High | I6: ID14,ID51
A7: S04 | B7: DailyObjects | C7: Internal decks | D7: Category strategy 3-yr + per-category economics (backpacks, wireless chargers, power banks, desks, watch straps, organisers) | E7: Google Drive (internal) | F7: 2026-07 | G7: Category roles & economics | H7: High | I7: Tab 5
A8: S05 | B8: DailyObjects | C8: Website | D8: Site taxonomy (cid URL structure), rewards, trendingOffers, gifting, corporate gifting, shop-by-Apple | E8: dailyobjects.com | F8: 2026-08 | G8: cid->category mapping, offers, loyalty | H8: Med (search-index) | I8: Tab 5; ID09,26,28,30,44
A9: S06 | B9: boAt | C9: Coupon/press | D9: BOATHEAD prepaid 5%; UPI cashback; RRP launch anchor; e-gift 8% | E9: grabon.in/boat-coupons | F9: 2026-08 | G9: Prepaid/UPI & anchoring tactics | H9: Reported | I9: ID07,12,15,32,44,53
A10: S07 | B10: Mokobara | C10: Coupon/review | D10: Moko Club Rs499/6mo; 30-day trial + warranty; luggage sets | E10: grabon.in/mokobara | F10: 2026-08 | G10: Membership, risk reversal, set pricing | H10: Reported | I10: ID39,40,03
A11: S08 | B11: Zouk | C11: Brand site | D11: Named bag+wallet combos up to 50%; prepaid incentives | E11: zouk.co.in | F11: 2026-08 | G11: Bag cross-sell combos | H11: Reported | I11: ID03,45
A12: S09 | B12: Casetify | C12: Coupon | D12: Auto multi-buy 15/20/30%; up to 50% accessories with a case | E12: couponfollow.com/site/casetify.com | F12: 2026-08 | G12: Case attach & multi-buy escalator | H12: Reported | I12: ID01,04,54
A13: S10 | B13: dbrand | C13: FAQ/press | D13: Grip+Prism bundle 15%; checkout screen-protector upsell; no-stack rule | E13: dbrand.com/support/faq/product-questions | F13: 2026-08 | G13: Bundle & checkout upsell, margin guardrail | H13: Reported | I13: ID08b,13,17,54
A14: S11 | B14: Bellroy | C14: Brand site | D14: Value sets; Tech Kit organiser attach | E14: bellroy.com/bundles | F14: 2026-08 | G14: Value sets & organiser attach | H14: Reported | I14: ID03,09,45
... A23: S20 | B23: Entrackr / BusinessToday | C23: Press | D23: FY25 rev Rs110Cr (+31%); AOV ~Rs1,800-2,000; repeat ~47%; 70%+ own web/app | E23: entrackr.com | F23: 2025 | G23: Business context & sizing | H23: Med | I23: Context; Tab 11

Sheet 14. GA4 Data Snapshot
A1: GA4 DATA SNAPSHOT (evidence base)
A2: OBSERVED. GA4 'DO - GA4' (273672074), via Windsor.ai, pulled 2026-08-10. Window 2025-08-01 to 2026-07-31. CVR/AOV/RPV are formula-driven.
A4: MONTHLY TREND
A5: Month | B5: Sessions | C5: Users | D5: New Users | E5: Add-to-Carts | F5: Checkouts | G5: Purchases (ecom) | H5: Transactions | I5: Revenue (Rs) | J5: CVR | K5: AOV (Rs)
A6: 2025-08 | B6: 4778202 | C6: 3150176 | D6: 2647949 | E6: 632504 | F6: 168112 | G6: 78318 | H6: 78318 | I6: 1.8242957e+08 | J6: =IF(B6=0,0,H6/B6) | K6: =IF(H6=0,0,I6/H6)
A7: 2025-09 | B7: 3707080 | C7: 2603854 | D7: 2107500 | E7: 303928 | F7: 93425 | G7: 33690 | H7: 33690 | I7: 69322773 | J7: =IF(B7=0,0,H7/B7) | K7: =IF(H7=0,0,I7/H7)
A8: 2025-10 | B8: 4189989 | C8: 2857269 | D8: 2394336 | E8: 380221 | F8: 109317 | G8: 39312 | H8: 39312 | I8: 84273748 | J8: =IF(B8=0,0,H8/B8) | K8: =IF(H8=0,0,I8/H8)
A9: 2025-11 | B9: 3480046 | C9: 2417126 | D9: 2005810 | E9: 412433 | F9: 103992 | G9: 37547 | H9: 37547 | I9: 91946942 | J9: =IF(B9=0,0,H9/B9) | K9: =IF(H9=0,0,I9/H9)
A10: 2025-12 | B10: 4299002 | C10: 2967009 | D10: 2459627 | E10: 446091 | F10: 133283 | G10: 40766 | H10: 40766 | I10: 98459311 | J10: =IF(B10=0,0,H10/B10) | K10: =IF(H10=0,0,I10/H10)
A11: 2026-01 | B11: 4360245 | C11: 3160229 | D11: 2700558 | E11: 452811 | F11: 121212 | G11: 35209 | H11: 35209 | I11: 91580318 | J11: =IF(B11=0,0,H11/B11) | K11: =IF(H11=0,0,I11/H11)
A12: 2026-02 | B12: 3870088 | C12: 2870261 | D12: 2425682 | E12: 531118 | F12: 133142 | G12: 33824 | H12: 30573 | I12: 80921704 | J12: =IF(B12=0,0,H12/B12) | K12: =IF(H12=0,0,I12/H12)
A13: 2026-03 | B13: 5538890 | C13: 3558510 | D13: 2892410 | E13: 1118162 | F13: 264405 | G13: 143823 | H13: 110360 | I13: 2.7152138e+08 | J13: =IF(B13=0,0,H13/B13) | K13: =IF(H13=0,0,I13/H13)
A14: 2026-04 | B14: 3845738 | C14: 2808802 | D14: 2321712 | E14: 391107 | F14: 95901 | G14: 36777 | H14: 29926 | I14: 77987308 | J14: =IF(B14=0,0,H14/B14) | K14: =IF(H14=0,0,I14/H14)
A15: 2026-05 | B15: 4134540 | C15: 2889760 | D15: 2346122 | E15: 423483 | F15: 107767 | G15: 49632 | H15: 39698 | I15: 96339976 | J15: =IF(B15=0,0,H15/B15) | K15: =IF(H15=0,0,I15/H15)
A16: 2026-06 | B16: 5715913 | C16: 4501368 | D16: 3989164 | E16: 382001 | F16: 94255 | G16: 43485 | H16: 35354 | I16: 92065794 | J16: =IF(B16=0,0,H16/B16) | K16: =IF(H16=0,0,I16/H16)
A17: 2026-07 | B17: 5953747 | C17: 4279633 | D17: 3716745 | E17: 513503 | F17: 126751 | G17: 50608 | H17: 42504 | I17: 1.0726006e+08 | J17: =IF(B17=0,0,H17/B17) | K17: =IF(H17=0,0,I17/H17)
A18: TOTAL | B18: =SUM(B6:B17) | C18: =SUM(C6:C17) | D18: =SUM(D6:D17) | E18: =SUM(E6:E17) | F18: =SUM(F6:F17) | G18: =SUM(G6:G17) | H18: =SUM(H6:H17) | I18: =SUM(I6:I17) | J18: =H18/B18 | K18: =I18/H18
A21: BY DEVICE
A22: Device | B22: Sessions | C22: Add-to-Carts | D22: Checkouts | E22: Transactions | F22: Revenue (Rs) | G22: CVR | H22: AOV (Rs) | I22: RPV (Rs)
A23: Mobile | B23: 49120510 | C23: 5403220 | D23: 1399681 | E23: 465801 | F23: 1.1004624e+09 | G23: =IF(B23=0,0,E23/B23) | H23: =IF(E23=0,0,F23/E23) | I23: =IF(B23=0,0,F23/B23)
A24: Desktop | B24: 4265707 | C24: 541173 | D24: 141363 | E24: 83754 | F24: 2.3322153e+08 | G24: =IF(B24=0,0,E24/B24) | H24: =IF(E24=0,0,F24/E24) | I24: =IF(B24=0,0,F24/B24)
A25: Tablet | B25: 396474 | C25: 42969 | D25: 10518 | E25: 3702 | F25: 10424981 | G25: =IF(B25=0,0,E25/B25) | H25: =IF(E25=0,0,F25/E25) | I25: =IF(B25=0,0,F25/B25)
A26: Other | B26: 239438 | C26: 0 | D26: 0 | E26: 0 | F26: 0 | G26: =IF(B26=0,0,E26/B26) | H26: =IF(E26=0,0,F26/E26) | I26: =IF(B26=0,0,F26/B26)
A29: BY CHANNEL
A30: Channel | B30: Sessions | C30: Add-to-Carts | D30: Transactions | E30: Revenue (Rs) | F30: CVR | G30: AOV (Rs) | H30: RPV (Rs)
A31: Direct | B31: 5814894 | C31: 1003157 | D31: 155517 | E31: 4.0697546e+08 | F31: =IF(B31=0,0,D31/B31) | G31: =IF(D31=0,0,E31/D31) | H31: =IF(B31=0,0,E31/B31)
A32: Paid Social | B32: 29240422 | C32: 1719430 | D32: 111480 | E32: 2.725193e+08 | F32: =IF(B32=0,0,D32/B32) | G32: =IF(D32=0,0,E32/D32) | H32: =IF(B32=0,0,E32/B32)
A33: Cross-network | B33: 7973460 | C33: 1836855 | D33: 96922 | E33: 2.0146663e+08 | F33: =IF(B33=0,0,D33/B33) | G33: =IF(D33=0,0,E33/D33) | H33: =IF(B33=0,0,E33/B33)
A34: Paid Search | B34: 2855905 | C34: 593396 | D34: 73763 | E34: 1.8454887e+08 | F34: =IF(B34=0,0,D34/B34) | G34: =IF(D34=0,0,E34/D34) | H34: =IF(B34=0,0,E34/B34)
A35: Organic Search | B35: 3686301 | C35: 367691 | D35: 54056 | E35: 1.2847155e+08 | F35: =IF(B35=0,0,D35/B35) | G35: =IF(D35=0,0,E35/D35) | H35: =IF(B35=0,0,E35/B35)
A36: Unassigned | B36: 1926947 | C36: 236940 | D36: 37705 | E36: 91529315 | F36: =IF(B36=0,0,D36/B36) | G36: =IF(D36=0,0,E36/D36) | H36: =IF(B36=0,0,E36/B36)
A37: Organic Social | B37: 1098650 | C37: 125758 | D37: 13535 | E37: 34078002 | F37: =IF(B37=0,0,D37/B37) | G37: =IF(D37=0,0,E37/D37) | H37: =IF(B37=0,0,E37/B37)
A38: Referral | B38: 358447 | C38: 47164 | D38: 5076 | E38: 11728922 | F38: =IF(B38=0,0,D38/B38) | G38: =IF(D38=0,0,E38/D38) | H38: =IF(B38=0,0,E38/B38)
A39: Organic Shopping | B39: 106133 | C39: 17067 | D39: 1963 | E39: 4023026.7 | F39: =IF(B39=0,0,D39/B39) | G39: =IF(D39=0,0,E39/D39) | H39: =IF(B39=0,0,E39/B39)
A40: Email | B40: 161294 | C40: 18986 | D40: 1941 | E40: 5730209.2 | F40: =IF(B40=0,0,D40/B40) | G40: =IF(D40=0,0,E40/D40) | H40: =IF(B40=0,0,E40/B40)
A41: Mobile Push | B41: 33623 | C41: 3456 | D41: 357 | E41: 877258.67 | F41: =IF(B41=0,0,D41/B41) | G41: =IF(D41=0,0,E41/D41) | H41: =IF(B41=0,0,E41/B41)
A42: Paid Other | B42: 23707 | C42: 3720 | D42: 319 | E42: 680989.15 | F42: =IF(B42=0,0,D42/B42) | G42: =IF(D42=0,0,E42/D42) | H42: =IF(B42=0,0,E42/B42)
... A46: Affiliates | B46: 3351 | C46: 326 | D46: 51 | E46: 116770.21 | F46: =IF(B46=0,0,D46/B46) | G46: =IF(D46=0,0,E46/D46) | H46: =IF(B46=0,0,E46/B46)
A49: NEW vs RETURNING
A50: Segment | B50: Sessions | C50: Transactions | D50: Revenue (Rs) | E50: CVR | F50: AOV (Rs)
A51: New | B51: 32900471 | C51: 227016 | D51: 5.1345832e+08 | E51: =IF(B51=0,0,C51/B51) | F51: =IF(C51=0,0,D51/C51)
A52: Returning | B52: 16940629 | C52: 299364 | D52: 7.701887e+08 | E52: =IF(B52=0,0,C52/B52) | F52: =IF(C52=0,0,D52/C52)
A53: (not set) | B53: 3433500 | C53: 26877 | D53: 60461871 | E53: =IF(B53=0,0,C53/B53) | F53: =IF(C53=0,0,D53/C53)
A56: SITEWIDE FUNNEL (key events)
A57: Step | B57: Events | C57: % of Views | D57: Step Conversion
A58: View Item | B58: 17961129 | C58: =B58/$B$58 | D58: -
A59: Add to Cart | B59: 5987294 | C59: =B59/$B$58 | D59: =B59/B58
A60: Begin Checkout | B60: 1546210 | C60: =B60/$B$58 | D60: =B60/B59
A61: Add Payment Info | B61: 1068241 | C61: =B61/$B$58 | D61: =B61/B60
A62: Purchase | B62: 622991 | C62: =B62/$B$58 | D62: =B62/B61
